Workbook
Name Slicer_Country_Name: #N/A

Sheet Data
A1: Country Name | B1: Country Code | C1: Series Name | D1: Series Code | E1: 2010 [YR2010] | F1: 2011 [YR2011] | G1: 2012 [YR2012] | H1: 2013 [YR2013] | I1: 2014 [YR2014] | J1: 2015 [YR2015] | K1: 2016 [YR2016] | L1: 2017 [YR2017] | M1: 2018 [YR2018] | N1: 2019 [YR2019] | O1: 2020 [YR2020] | P1: 2021 [YR2021] | Q1: 2022 [YR2022] | R1: 2023 [YR2023] | S1: 2024 [YR2024] | T1: 2025 [YR2025]
A2: Pakistan | B2: PAK | C2: GDP (current US$) | D2: NY.GDP.MKTP.CD | E2: 1.9670962e+11 | F2: 2.3058658e+11 | G2: 2.5010697e+11 | H2: 2.5865723e+11 | I2: 2.7139047e+11 | J2: 2.9996359e+11 | K2: 3.1363e+11 | L2: 3.3920553e+11 | M2: 3.5612817e+11 | N2: 3.2090947e+11 | O2: 3.0042561e+11 | P2: 3.4851665e+11 | Q2: 3.748903e+11 | R2: 3.3668635e+11 | S2: 3.7174709e+11 | T2: 4.0730721e+11
A3: Pakistan | B3: PAK | C3: GDP growth (annual %) | D3: NY.GDP.MKTP.KD.ZG | E3: 1.5017175 | F3: 2.6801169 | G3: 3.0275839 | H3: 4.366865 | I3: 4.1164282 | J3: 4.2179421 | K3: 6.5738383 | L3: 4.4326259 | M3: 6.1517026 | N3: 2.4976369 | O3: -1.2740874 | P3: 6.5138858 | Q3: 4.7781069 | R3: -0.414936 | S3: 3.081763 | T3: 3.6984267
A4: Pakistan | B4: PAK | C4: Inflation, consumer prices (annual %) | D4: FP.CPI.TOTL.ZG | E4: 12.938871 | F4: 11.916093 | G4: 9.6823519 | H4: 7.6921561 | I4: 7.189384 | J4: 2.5293282 | K4: 3.7651192 | L4: 4.0853737 | M4: 5.0780573 | N4: 10.578031 | O4: 9.7401162 | P4: 9.4964158 | Q4: 19.87386 | R4: 30.768128 | S4: 12.632532 | T4: 3.5455521
A5: Pakistan | B5: PAK | C5: Unemployment, total (% of total labor force) (modeled ILO estimate) | D5: SL.UEM.TOTL.ZS | E5: 0.653 | F5: 0.796 | G5: 3.667 | H5: 2.954 | I5: 1.827 | J5: 3.566 | K5: 2.285 | L5: 3.204 | M5: 4.083 | N5: 4.83 | O5: 5.994 | P5: 6.338 | Q5: 5.291 | R5: 5.237 | S5: 5.492 | T5: 5.42
A6: Pakistan | B6: PAK | C6: Lending interest rate (%) | D6: FR.INR.LEND | E6: 14.0425 | F6: 14.419167 | G6: 13.519167 | H6: 11.985833 | I6: 11.73 | J6: 10.155833 | K6: 8.755 | L6: 8.21 | M6: 8.5308333 | N6: 12.233055 | O6: 10.757749 | P6: 8.6659742 | Q6: .. | R6: .. | S6: .. | T6: ..
A7: Pakistan | B7: PAK | C7: Official exchange rate (LCU per US$, period average) | D7: PA.NUS.FCRF | E7: 85.193816 | F7: 86.343383 | G7: 93.395197 | H7: 101.6289 | I7: 101.10009 | J7: 102.76927 | K7: 104.76912 | L7: 105.45516 | M7: 121.82407 | N7: 150.03625 | O7: 161.83848 | P7: 162.90625 | Q7: 204.86719 | R7: 280.35611 | S7: 278.58072 | T7: 281.143
A8: Pakistan | B8: PAK | C8: Exports of goods and services (% of GDP) | D8: NE.EXP.GNFS.ZS | E8: 12.637225 | F8: 13.482555 | G8: 11.873964 | H8: 12.177499 | I8: 11.194972 | J8: 9.974571 | K8: 8.7367164 | L8: 8.2216113 | M8: 8.5817996 | N8: 9.3908635 | O8: 9.2985594 | P8: 9.0515999 | Q8: 10.54059 | R8: 10.493959 | S8: 10.385503 | T8: 9.9852067
A9: Pakistan | B9: PAK | C9: Imports of goods and services (% of GDP) | D9: NE.IMP.GNFS.ZS | E9: 19.351777 | F9: 18.880083 | G9: 19.445009 | H9: 18.712775 | I9: 18.274854 | J9: 16.713615 | K9: 15.964862 | L9: 17.250424 | M9: 19.044257 | N9: 19.514713 | O9: 17.417721 | P9: 17.978821 | Q9: 22.490763 | R9: 17.973734 | S9: 17.179828 | T9: 17.208331
A10: Pakistan | B10: PAK | C10: Foreign direct investment, net inflows (BoP, current US$) | D10: BX.KLT.DINV.CD.WD | E10: 2022000000 | F10: 1326000000 | G10: 859000000 | H10: 1333000000 | I10: 1887000000 | J10: 1673000000 | K10: 2576000000 | L10: 2496000000 | M10: 1737000000 | N10: 2234000000 | O10: 2057000000 | P10: 2147000000 | Q10: 1462000000 | R10: 2048000000 | S10: 2665000000 | T10: 1852000000
A11: Pakistan | B11: PAK | C11: Population, total | D11: SP.POP.TOTL | E11: 199239047 | F11: 203746065 | G11: 207667125 | H11: 211073978 | I11: 214264647 | J11: 217290883 | K11: 220138869 | L11: 223273967 | M11: 226928892 | N11: 230800899 | O11: 235001746 | P11: 239477801 | Q11: 243700667 | R11: 247504495 | S11: 251269164 | T11: 255219554
A12: India | B12: IND | C12: GDP (current US$) | D12: NY.GDP.MKTP.CD | E12: 1.6756155e+12 | F12: 1.8230518e+12 | G12: 1.8276376e+12 | H12: 1.8567215e+12 | I12: 2.0391265e+12 | J12: 2.1035884e+12 | K12: 2.2947969e+12 | L12: 2.6514743e+12 | M12: 2.7029296e+12 | N12: 2.8356063e+12 | O12: 2.6748516e+12 | P12: 3.1672706e+12 | Q12: 3.2499385e+12 | R12: 3.500906e+12 | S12: 3.7608135e+12 | T12: 3.9560671e+12
A13: India | B13: IND | C13: GDP growth (annual %) | D13: NY.GDP.MKTP.KD.ZG | E13: 8.4975847 | F13: 5.2413162 | G13: 5.4563876 | H13: 6.3861064 | I13: 7.4102276 | J13: 7.9962538 | K13: 8.2563055 | L13: 6.7953834 | M13: 6.4538513 | N13: 3.8714369 | O13: -5.7777247 | P13: 9.6895925 | Q13: 7.609365 | R13: 7.2102246 | S13: 7.0992789 | T13: 7.5666618
A14: India | B14: IND | C14: Inflation, consumer prices (annual %) | D14: FP.CPI.TOTL.ZG | E14: 11.98939 | F14: 8.9117934 | G14: 9.4789969 | H14: 10.017878 | I14: 6.6656567 | J14: 4.9069734 | K14: 4.9482163 | L14: 3.3281734 | M14: 3.9388265 | N14: 3.7295057 | O14: 6.6234368 | P14: 5.1314075 | Q14: 6.6990341 | R14: 5.6491432 | S14: 4.9530355 | T14: 2.3988495
A15: India | B15: IND | C15: Unemployment, total (% of total labor force) (modeled ILO estimate) | D15: SL.UEM.TOTL.ZS | E15: 7.631 | F15: 7.609 | G15: 7.645 | H15: 7.678 | I15: 7.656 | J15: 7.629 | K15: 7.611 | L15: 7.626 | M15: 7.652 | N15: 6.51 | O15: 7.859 | P15: 6.38 | Q15: 4.822 | R15: 4.172 | S15: 4.173 | T15: 4.219
A16: India | B16: IND | C16: Lending interest rate (%) | D16: FR.INR.LEND | E16: 8.33335 | F16: 10.166667 | G16: 10.604167 | H16: 10.291667 | I16: 10.25 | J16: 10.008333 | K16: 9.6725 | L16: 9.5083333 | M16: 9.4541667 | N16: 9.46625 | O16: 9.15 | P16: 8.6983333 | Q16: 8.5671429 | R16: .. | S16: .. | T16: ..
A17: India | B17: IND | C17: Official exchange rate (LCU per US$, period average) | D17: PA.NUS.FCRF | E17: 45.725812 | F17: 46.670467 | G17: 53.437233 | H17: 58.597845 | I17: 61.029514 | J17: 64.151944 | K17: 67.195313 | L17: 65.121569 | M17: 68.389467 | N17: 70.420341 | O17: 74.099567 | P17: 73.918013 | Q17: 78.604491 | R17: 82.599276 | S17: 83.669282 | T17: 87.158448
A18: India | B18: IND | C18: Exports of goods and services (% of GDP) | D18: NE.EXP.GNFS.ZS | E18: 22.400933 | F18: 24.540411 | G18: 24.534431 | H18: 25.430861 | I18: 22.967963 | J18: 19.813189 | K18: 19.158235 | L18: 18.791765 | M18: 19.927829 | N18: 18.664265 | O18: 18.682477 | P18: 21.399158 | Q18: 24.040172 | R18: 22.354802 | S18: 22.063982 | T18: 22.263041
A19: India | B19: IND | C19: Imports of goods and services (% of GDP) | D19: NE.IMP.GNFS.ZS | E19: 26.854273 | F19: 31.083469 | G19: 31.259291 | H19: 28.413271 | I19: 25.954223 | J19: 22.109725 | K19: 20.924251 | L19: 21.950732 | M19: 23.689141 | N19: 21.241139 | O19: 19.075628 | P19: 24.02393 | Q19: 26.657767 | R19: 23.96815 | S19: 23.852709 | T19: 24.00516
A20: India | B20: IND | C20: Foreign direct investment, net inflows (BoP, current US$) | D20: BX.KLT.DINV.CD.WD | E20: 2.7396885e+10 | F20: 3.6498655e+10 | G20: 2.3995685e+10 | H20: 2.8153031e+10 | I20: 3.4576644e+10 | J20: 4.4009492e+10 | K20: 4.4458572e+10 | L20: 3.9966091e+10 | M20: 4.2117451e+10 | N20: 5.0610647e+10 | O20: 6.4362365e+10 | P20: 4.4727278e+10 | Q20: 4.9940258e+10 | R20: 2.8086194e+10 | S20: 2.7139853e+10 | T20: 3.9097233e+10
A21: India | B21: IND | C21: Population, total | D21: SP.POP.TOTL | E21: 1243481564 | F21: 1261224954 | G21: 1278674502 | H21: 1295829511 | I21: 1312277191 | J21: 1328024498 | K21: 1343944296 | L21: 1359657400 | M21: 1374659064 | N21: 1389030312 | O21: 1402617695 | P21: 1414203896 | Q21: 1425423212 | R21: 1438069596 | S21: 1450935791 | T21: 1463865525
A22: China | B22: CHN | C22: GDP (current US$) | D22: NY.GDP.MKTP.CD | E22: 6.1925649e+12 | F22: 7.6717572e+12 | G22: 8.6736647e+12 | H22: 9.7431242e+12 | I22: 1.0674533e+13 | J22: 1.1280815e+13 | K22: 1.1456024e+13 | L22: 1.2537559e+13 | M22: 1.4147766e+13 | N22: 1.4560167e+13 | O22: 1.4996414e+13 | P22: 1.8201699e+13 | Q22: 1.8316765e+13 | R22: 1.8270357e+13 | S22: 1.8729668e+13 | T22: 1.9498039e+13
A23: China | B23: CHN | C23: GDP growth (annual %) | D23: NY.GDP.MKTP.KD.ZG | E23: 10.59169 | F23: 9.4620525 | G23: 7.8578201 | H23: 7.7784295 | I23: 7.4610074 | J23: 6.9816226 | K23: 6.7736887 | L23: 6.8912392 | M23: 6.7578061 | N23: 6.0673781 | O23: 2.3395039 | P23: 8.5703841 | Q23: 3.1338544 | R23: 5.4160033 | S23: 4.9583038 | T23: 4.9599489
A24: China | B24: CHN | C24: Inflation, consumer prices (annual %) | D24: FP.CPI.TOTL.ZG | E24: 3.1753248 | F24: 5.5538989 | G24: 2.6195243 | H24: 2.62105 | I24: 1.9216416 | J24: 1.4370238 | K24: 2.0000018 | L24: 1.593136 | M24: 2.0747904 | N24: 2.8992342 | O24: 2.4194219 | P24: 0.98101514 | Q24: 1.9735756 | R24: 0.23483683 | S24: 0.21812894 | T24: 0.059564692
A25: China | B25: CHN | C25: Unemployment, total (% of total labor force) (modeled ILO estimate) | D25: SL.UEM.TOTL.ZS | E25: 4.53 | F25: 4.55 | G25: 4.58 | H25: 4.6 | I25: 4.63 | J25: 4.65 | K25: 4.56 | L25: 4.47 | M25: 4.31 | N25: 4.56 | O25: 5 | P25: 4.55 | Q25: 4.98 | R25: 4.67 | S25: 4.59 | T25: 4.615
A26: China | B26: CHN | C26: Lending interest rate (%) | D26: FR.INR.LEND | E26: 5.81 | F26: 6.56 | G26: 6 | H26: 6 | I26: 5.6 | J26: 4.35 | K26: 4.35 | L26: 4.35 | M26: 4.35 | N26: 4.35 | O26: 4.35 | P26: 4.35 | Q26: 4.35 | R26: 4.35 | S26: 4.35 | T26: ..
A27: China | B27: CHN | C27: Official exchange rate (LCU per US$, period average) | D27: PA.NUS.FCRF | E27: 6.770269 | F27: 6.4614613 | G27: 6.3123328 | H27: 6.1957583 | I27: 6.1434341 | J27: 6.2274887 | K27: 6.6444778 | L27: 6.7587551 | M27: 6.6159572 | N27: 6.908385 | O27: 6.9007673 | P27: 6.4489752 | Q27: 6.7371581 | R27: 7.0839984 | S27: 7.1974911 | T27: 7.1898474
A28: China | B28: CHN | C28: Exports of goods and services (% of GDP) | D28: NE.EXP.GNFS.ZS | E28: 26.722745 | F28: 26.151883 | G28: 25.076704 | H28: 24.163343 | I28: 23.071977 | J28: 20.939064 | K28: 19.203651 | L28: 19.33563 | M28: 18.77052 | N28: 18.139822 | O28: 18.269601 | P28: 19.435056 | Q28: 20.227756 | R28: 19.402309 | S28: 20.442828 | T28: 21.071198
A29: China | B29: CHN | C29: Imports of goods and services (% of GDP) | D29: NE.IMP.GNFS.ZS | E29: 23.131327 | F29: 23.793944 | G29: 22.403509 | H29: 21.752698 | I29: 20.99648 | J29: 17.758121 | K29: 16.97352 | L29: 17.615222 | M29: 18.123865 | N29: 17.314613 | O29: 16.068177 | P29: 17.207823 | Q29: 17.2848 | R29: 17.336841 | S29: 17.513232 | T29: 16.88519
A30: China | B30: CHN | C30: Foreign direct investment, net inflows (BoP, current US$) | D30: BX.KLT.DINV.CD.WD | E30: 2.4370343e+11 | F30: 2.8007222e+11 | G30: 2.4121387e+11 | H30: 2.9092843e+11 | I30: 2.6809718e+11 | J30: 2.4248933e+11 | K30: 1.7474958e+11 | L30: 1.6608376e+11 | M30: 2.3536505e+11 | N30: 1.8716982e+11 | O30: 2.5309562e+11 | P30: 3.4407498e+11 | Q30: 1.9020379e+11 | R30: 5.1338077e+10 | S30: 4.2646542e+10 | T30: 7.9979866e+10
A31: China | B31: CHN | C31: Population, total | D31: SP.POP.TOTL | E31: 1337705000 | F31: 1345035000 | G31: 1354190000 | H31: 1363240000 | I31: 1371860000 | J31: 1379860000 | K31: 1387790000 | L31: 1396215000 | M31: 1402760000 | N31: 1407745000 | O31: 1411100000 | P31: 1412360000 | Q31: 1412175000 | R31: 1410710000 | S31: 1408975000 | T31: 1406585000
A32: Japan | B32: JPN | C32: GDP (current US$) | D32: NY.GDP.MKTP.CD | E32: 5.8115781e+12 | F32: 6.2794226e+12 | G32: 6.3338039e+12 | H32: 5.272297e+12 | I32: 4.9857633e+12 | J32: 4.5344386e+12 | K32: 5.1103574e+12 | L32: 5.0382316e+12 | M32: 5.1542937e+12 | N32: 5.245755e+12 | O32: 5.1891975e+12 | P32: 5.2259335e+12 | Q32: 4.4479762e+12 | R32: 4.3848543e+12 | S32: 4.1900082e+12 | T32: 4.435163e+12
A33: Japan | B33: JPN | C33: GDP growth (annual %) | D33: NY.GDP.MKTP.KD.ZG | E33: 4.1364559 | F33: -0.20035785 | G33: 1.6489345 | H33: 1.9972765 | I33: 0.90591549 | J33: 1.7999774 | K33: 0.7049865 | L33: 1.6234506 | M33: 0.83414385 | N33: -0.30849692 | O33: -4.2832794 | P33: 3.5641953 | Q33: 1.3316475 | R33: 0.7207853 | S33: -0.24008424 | T33: 1.1931129
A34: Japan | B34: JPN | C34: Inflation, consumer prices (annual %) | D34: FP.CPI.TOTL.ZG | E34: -0.72824321 | F34: -0.27245562 | G34: -0.04406451 | H34: 0.33503791 | I34: 2.7592267 | J34: 0.79527963 | K34: -0.12725884 | L34: 0.4841998 | M34: 0.9890946 | N34: 0.46877616 | O34: -0.024995834 | P34: -0.23335278 | Q34: 2.4977028 | R34: 3.2681337 | S34: 2.7385368 | T34: 3.1725303
A35: Japan | B35: JPN | C35: Unemployment, total (% of total labor force) (modeled ILO estimate) | D35: SL.UEM.TOTL.ZS | E35: 5.102 | F35: 4.55 | G35: 4.358 | H35: 4.038 | I35: 3.589 | J35: 3.385 | K35: 3.132 | L35: 2.822 | M35: 2.467 | N35: 2.351 | O35: 2.809 | P35: 2.808 | Q35: 2.614 | R35: 2.6 | S35: 2.5 | T35: 2.451
A36: Japan | B36: JPN | C36: Lending interest rate (%) | D36: FR.INR.LEND | E36: 1.5983333 | F36: 1.5009167 | G36: 1.4075 | H36: 1.30375 | I36: 1.2191667 | J36: 1.1428333 | K36: 1.04475 | L36: 0.994 | M36: .. | N36: .. | O36: .. | P36: .. | Q36: .. | R36: .. | S36: .. | T36: ..
A37: Japan | B37: JPN | C37: Official exchange rate (LCU per US$, period average) | D37: PA.NUS.FCRF | E37: 87.779875 | F37: 79.80702 | G37: 79.790455 | H37: 97.595658 | I37: 105.94478 | J37: 121.04403 | K37: 108.7929 | L37: 112.16614 | M37: 110.42318 | N37: 109.00967 | O37: 106.77458 | P37: 109.75432 | Q37: 131.49814 | R37: 140.4911 | S37: 151.36629 | T37: 149.65793
A38: Japan | B38: JPN | C38: Exports of goods and services (% of GDP) | D38: NE.EXP.GNFS.ZS | E38: 14.782738 | F38: 14.664526 | G38: 14.273915 | H38: 15.603709 | I38: 17.107863 | J38: 17.09211 | K38: 15.722396 | L38: 17.215825 | M38: 17.911143 | N38: 17.037797 | O38: 15.12869 | P38: 17.461985 | Q38: 20.647867 | R38: 21.05931 | S38: 21.979909 | T38: ..
A39: Japan | B39: JPN | C39: Imports of goods and services (% of GDP) | D39: NE.IMP.GNFS.ZS | E39: 13.457277 | F39: 15.306859 | G39: 15.900384 | H39: 17.98766 | I39: 19.656462 | J39: 17.635521 | K39: 14.933883 | L39: 16.473008 | M39: 17.892431 | N39: 17.3205 | O39: 15.390532 | P39: 17.963407 | Q39: 24.212764 | R39: 22.535773 | S39: 22.873029 | T39: ..
A40: Japan | B40: JPN | C40: Foreign direct investment, net inflows (BoP, current US$) | D40: BX.KLT.DINV.CD.WD | E40: 7.4409793e+09 | F40: -8.5071704e+08 | G40: 5.4696269e+08 | H40: 1.0648442e+10 | I40: 1.9752249e+10 | J40: 5.2522184e+09 | K40: 4.0954181e+10 | L40: 1.8802251e+10 | M40: 2.5289368e+10 | N40: 3.9960544e+10 | O40: 6.2584719e+10 | P40: 3.5027164e+10 | Q40: 4.8153833e+10 | R40: 2.0007989e+10 | S40: 1.8874094e+10 | T40: 4.5805721e+10
A41: Japan | B41: JPN | C41: Population, total | D41: SP.POP.TOTL | E41: 128070000 | F41: 127833000 | G41: 127629000 | H41: 127445000 | I41: 127276000 | J41: 127141000 | K41: 127076000 | L41: 126972000 | M41: 126811000 | N41: 126633000 | O41: 126261000 | P41: 125681593 | Q41: 125124989 | R41: 124516650 | S41: 123975371 | T41: 123366734
A42: Indonesia | B42: IDN | C42: GDP (current US$) | D42: NY.GDP.MKTP.CD | E42: 7.5509416e+11 | F42: 8.929691e+11 | G42: 9.1786991e+11 | H42: 9.1252414e+11 | I42: 8.9081476e+11 | J42: 8.6085423e+11 | K42: 9.3187736e+11 | L42: 1.0156187e+12 | M42: 1.0422715e+12 | N42: 1.1190999e+12 | O42: 1.0590548e+12 | P42: 1.1865097e+12 | Q42: 1.3191012e+12 | R42: 1.3711669e+12 | S42: 1.3963018e+12 | T42: 1.4456426e+12
A43: Indonesia | B43: IDN | C43: GDP growth (annual %) | D43: NY.GDP.MKTP.KD.ZG | E43: 6.2238542 | F43: 6.1697842 | G43: 6.0300507 | H43: 5.5572637 | I43: 5.0066684 | J43: 4.8763223 | K43: 5.0330692 | L43: 5.0697859 | M43: 5.1742915 | N43: 5.0192877 | O43: -2.0655118 | P43: 3.7028856 | Q43: 5.3071972 | R43: 5.0488312 | S43: 5.0325748 | T43: 5.108089
A44: Indonesia | B44: IDN | C44: Inflation, consumer prices (annual %) | D44: FP.CPI.TOTL.ZG | E44: 5.1342064 | F44: 5.3560485 | G44: 4.2795143 | H44: 6.4124946 | I44: 6.3949288 | J44: 6.3631206 | K44: 3.5258045 | L44: 3.8087986 | M44: 3.1983476 | N44: 3.0305846 | O44: 1.9198353 | P44: 1.5600788 | Q44: 4.2094646 | R44: 3.6693865 | S44: 2.1815127 | T44: 1.9133344
A45: Indonesia | B45: IDN | C45: Unemployment, total (% of total labor force) (modeled ILO estimate) | D45: SL.UEM.TOTL.ZS | E45: 5.614 | F45: 5.153 | G45: 4.468 | H45: 4.336 | I45: 4.049 | J45: 4.514 | K45: 4.301 | L45: 3.783 | M45: 4.387 | N45: 3.59 | O45: 4.255 | P45: 3.827 | Q45: 3.462 | R45: 3.308 | S45: 3.301 | T45: 3.237
A46: Indonesia | B46: IDN | C46: Lending interest rate (%) | D46: FR.INR.LEND | E46: 13.251667 | F46: 12.403333 | G46: 11.795 | H46: 11.6575 | I46: 12.605 | J46: 12.6625 | K46: 11.888333 | L46: 11.073333 | M46: 10.536667 | N46: 10.365833 | O46: 9.5441667 | P46: 8.9225 | Q46: 8.52 | R46: 8.9266667 | S46: 8.7956878 | T46: 8.5015832
A47: Indonesia | B47: IDN | C47: Official exchange rate (LCU per US$, period average) | D47: PA.NUS.FCRF | E47: 9090.4333 | F47: 8770.4333 | G47: 9386.6292 | H47: 10461.24 | I47: 11865.211 | J47: 13389.413 | K47: 13308.327 | L47: 13380.834 | M47: 14236.939 | N47: 14147.671 | O47: 14582.203 | P47: 14308.144 | Q47: 14849.854 | R47: 15236.885 | S47: 15855.448 | T47: 16477.865
A48: Indonesia | B48: IDN | C48: Exports of goods and services (% of GDP) | D48: NE.EXP.GNFS.ZS | E48: 24.299031 | F48: 26.327353 | G48: 24.594379 | H48: 23.923576 | I48: 23.665985 | J48: 21.160179 | K48: 19.088994 | L48: 20.177304 | M48: 21.002746 | N48: 18.591528 | O48: 17.331168 | P48: 21.416556 | Q48: 24.502912 | R48: 21.808563 | S48: 22.309649 | T48: 22.846548
A49: Indonesia | B49: IDN | C49: Imports of goods and services (% of GDP) | D49: NE.IMP.GNFS.ZS | E49: 22.402243 | F49: 23.85266 | G49: 24.98852 | H49: 24.713796 | I49: 24.414191 | J49: 20.777461 | K49: 18.332348 | L49: 19.178193 | M49: 22.071562 | N49: 19.03625 | O49: 15.641007 | P49: 18.788203 | Q49: 20.961759 | R49: 19.651913 | S49: 20.500289 | T49: 20.544659
A50: Indonesia | B50: IDN | C50: Foreign direct investment, net inflows (BoP, current US$) | D50: BX.KLT.DINV.CD.WD | E50: 1.5292009e+10 | F50: 2.0564938e+10 | G50: 2.1200779e+10 | H50: 2.3281742e+10 | I50: 2.5120732e+10 | J50: 1.9779128e+10 | K50: 4.5417137e+09 | L50: 2.0510311e+10 | M50: 1.8909826e+10 | N50: 2.4993552e+10 | O50: 1.9175078e+10 | P50: 2.121308e+10 | Q50: 2.470203e+10 | R50: 2.1543359e+10 | S50: 2.4275445e+10 | T50: 2.2283232e+10
A51: Indonesia | B51: IDN | C51: Population, total | D51: SP.POP.TOTL | E51: 246305322 | F51: 249470032 | G51: 252698525 | H51: 255852467 | I51: 258877399 | J51: 261799249 | K51: 264627418 | L51: 267346658 | M51: 269951846 | N51: 272489381 | O51: 274814866 | P51: 276758053 | Q51: 278830529 | R51: 281190067 | S51: 283487931 | T51: 285721236
... A59: Malaysia | B59: MYS | C59: Imports of goods and services (% of GDP) | D59: NE.IMP.GNFS.ZS | E59: 71.01447 | F59: 69.682242 | G59: 68.541841 | H59: 67.09195 | I59: 64.518733 | J59: 61.921382 | K59: 60.123565 | L59: 63.143431 | M59: 61.847654 | N59: 57.750795 | O59: 55.210247 | P59: 63.402939 | Q59: 69.616807 | R59: 63.914508 | S59: 66.021486 | T59: 65.428631
A60: Malaysia | B60: MYS | C60: Foreign direct investment, net inflows (BoP, current US$) | D60: BX.KLT.DINV.CD.WD | E60: 1.0885802e+10 | F60: 1.5119439e+10 | G60: 8.8957743e+09 | H60: 1.129628e+10 | I60: 1.0619432e+10 | J60: 9.8571621e+09 | K60: 1.347009e+10 | L60: 9.3684698e+09 | M60: 8.3044807e+09 | N60: 9.1549217e+09 | O60: 4.0587697e+09 | P60: 2.0245157e+10 | Q60: 1.5027993e+10 | R60: 7.9186011e+09 | S60: 1.5593246e+10 | T60: ..
A61: Malaysia | B61: MYS | C61: Population, total | D61: SP.POP.TOTL | E61: 28655776 | F61: 29162039 | G61: 29662831 | H61: 30174265 | I61: 30696137 | J61: 31232798 | K61: 31789685 | L61: 32355644 | M61: 32910967 | N61: 33440596 | O61: 33889558 | P61: 34282399 | Q61: 34695493 | R61: 35126298 | S61: 35557673 | T61: 35977838
A62: Germany | B62: DEU | C62: GDP (current US$) | D62: NY.GDP.MKTP.CD | E62: 3.4670938e+12 | F62: 3.8235758e+12 | G62: 3.5964832e+12 | H62: 3.8070238e+12 | I62: 3.9648707e+12 | J62: 3.4250996e+12 | K62: 3.5367879e+12 | L62: 3.7653516e+12 | M62: 4.0554332e+12 | N62: 3.9598948e+12 | O62: 3.941399e+12 | P62: 4.355252e+12 | Q62: 4.2010217e+12 | R62: 4.5622075e+12 | S62: 4.6855926e+12 | T62: 5.0509229e+12
A63: Germany | B63: DEU | C63: GDP growth (annual %) | D63: NY.GDP.MKTP.KD.ZG | E63: 4.1346378 | F63: 3.7579688 | G63: 0.46351204 | H63: 0.39699558 | I63: 2.180186 | J63: 1.663006 | K63: 2.2222222 | L63: 2.7979067 | M63: 1.135696 | N63: 0.9777347 | O63: -4.1319144 | P63: 3.9099999 | Q63: 1.8092581 | R63: -0.86964758 | S63: -0.4958519 | T63: 0.23957834
A64: Germany | B64: DEU | C64: Inflation, consumer prices (annual %) | D64: FP.CPI.TOTL.ZG | E64: 1.1038104 | F64: 2.0751728 | G64: 2.0084888 | H64: 1.5047233 | I64: 0.906794 | J64: 0.51442614 | K64: 0.49174701 | L64: 1.5094949 | M64: 1.7321688 | N64: 1.4456598 | O64: 0.14487793 | P64: 3.0666667 | Q64: 6.8725744 | R64: 5.9464367 | S64: 2.2564981 | T64: 2.1717877
A65: Germany | B65: DEU | C65: Unemployment, total (% of total labor force) (modeled ILO estimate) | D65: SL.UEM.TOTL.ZS | E65: 7.043 | F65: 5.967 | G65: 5.372 | H65: 5.316 | I65: 4.979 | J65: 4.612 | K65: 4.104 | L65: 3.781 | M65: 3.384 | N65: 3.163 | O65: 3.881 | P65: 3.594 | Q65: 3.137 | R65: 3.071 | S65: 3.4 | T65: 3.711
A66: Germany | B66: DEU | C66: Lending interest rate (%) | D66: FR.INR.LEND | E66: .. | F66: .. | G66: .. | H66: .. | I66: .. | J66: .. | K66: .. | L66: .. | M66: .. | N66: .. | O66: .. | P66: .. | Q66: .. | R66: .. | S66: .. | T66: ..
A67: Germany | B67: DEU | C67: Official exchange rate (LCU per US$, period average) | D67: PA.NUS.FCRF | E67: 0.75430899 | F67: 0.7184139 | G67: 0.77833812 | H67: 0.75294512 | I67: 0.7527282 | J67: 0.90129642 | K67: 0.90342144 | L67: 0.88520551 | M67: 0.84677267 | N67: 0.89327626 | O67: 0.8755064 | P67: 0.84549414 | Q67: 0.94962375 | R67: 0.92483956 | S67: 0.92388955 | T67: 0.88496896
A68: Germany | B68: DEU | C68: Exports of goods and services (% of GDP) | D68: NE.EXP.GNFS.ZS | E68: 39.495347 | F68: 41.643629 | G68: 42.685583 | H68: 41.680284 | I68: 41.693668 | J68: 42.585398 | K68: 41.635542 | L68: 42.202958 | M68: 42.496891 | N68: 42.340244 | O68: 39.119807 | P68: 42.519838 | Q68: 45.628404 | R68: 42.967262 | S68: 41.434059 | T68: 40.434774
A69: Germany | B69: DEU | C69: Imports of goods and services (% of GDP) | D69: NE.IMP.GNFS.ZS | E69: 34.389889 | F69: 36.789374 | G69: 36.646066 | H69: 35.905745 | I69: 35.154684 | J69: 35.171184 | K69: 34.370448 | L69: 35.251882 | M69: 36.628335 | N69: 36.732998 | O69: 33.813726 | P69: 37.399697 | Q69: 43.15735 | R69: 38.995286 | S69: 37.656671 | T69: 38.078037
A70: Germany | B70: DEU | C70: Foreign direct investment, net inflows (BoP, current US$) | D70: BX.KLT.DINV.CD.WD | E70: 8.6037502e+10 | F70: 9.7535404e+10 | G70: 6.5443088e+10 | H70: 6.7199694e+10 | I70: 1.735672e+10 | J70: 6.2418994e+10 | K70: 5.8132711e+10 | L70: 1.087865e+11 | M70: 1.6225094e+11 | N70: 7.5463438e+10 | O70: 1.7678102e+11 | P70: 1.2760983e+11 | Q70: 7.657177e+10 | R70: 9.0884108e+10 | S70: 6.2637242e+10 | T70: 9.5190854e+10
A71: Germany | B71: DEU | C71: Population, total | D71: SP.POP.TOTL | E71: 81776930 | F71: 80274983 | G71: 80425823 | H71: 80645605 | I71: 80982500 | J71: 81686611 | K71: 82348669 | L71: 82657002 | M71: 82905782 | N71: 83092962 | O71: 83160871 | P71: 83196078 | Q71: 83177813 | R71: 83287273 | S71: 83516593 | T71: 83491249
A72: United Kingdom | B72: GBR | C72: GDP (current US$) | D72: NY.GDP.MKTP.CD | E72: 2.4967407e+12 | F72: 2.67559e+12 | G72: 2.719716e+12 | H72: 2.7969083e+12 | I72: 3.0853622e+12 | J72: 2.9455799e+12 | K72: 2.7068076e+12 | L72: 2.6991184e+12 | M72: 2.897028e+12 | N72: 2.8757101e+12 | O72: 2.7240015e+12 | P72: 3.1945592e+12 | Q72: 3.1812444e+12 | R72: 3.4207967e+12 | S72: 3.6955395e+12 | T72: 4.0025875e+12
A73: United Kingdom | B73: GBR | C73: GDP growth (annual %) | D73: NY.GDP.MKTP.KD.ZG | E73: 2.2605446 | F73: 0.85143774 | G73: 1.5282603 | H73: 1.7184696 | I73: 3.1601735 | J73: 2.1404056 | K73: 2.2065202 | L73: 3.0232222 | M73: 1.551331 | N73: 1.256299 | O73: -10.047897 | P73: 8.5431118 | Q73: 5.1497039 | R73: 0.27165005 | S73: 1.0802772 | T73: 1.3884421
A74: United Kingdom | B74: GBR | C74: Inflation, consumer prices (annual %) | D74: FP.CPI.TOTL.ZG | E74: 2.4926547 | F74: 3.8561124 | G74: 2.5732348 | H74: 2.2916667 | I74: 1.4511202 | J74: 0.36804684 | K74: 1.0084174 | L74: 2.5577558 | M74: 2.2928399 | N74: 1.7381046 | O74: 0.9894867 | P74: 2.5183711 | Q74: 7.9220488 | R74: 6.7939671 | S74: 3.2715729 | T74: 3.8830688
A75: United Kingdom | B75: GBR | C75: Unemployment, total (% of total labor force) (modeled ILO estimate) | D75: SL.UEM.TOTL.ZS | E75: 7.973 | F75: 8.195 | G75: 8.279 | H75: 7.752 | I75: 6.398 | J75: 5.552 | K75: 4.909 | L75: 4.501 | M75: 4.145 | N75: 3.657 | O75: 4.472 | P75: 4.864 | Q75: 3.768 | R75: 4.025 | S75: 4.361 | T75: 4.746
A76: United Kingdom | B76: GBR | C76: Lending interest rate (%) | D76: FR.INR.LEND | E76: 0.5 | F76: 0.5 | G76: 0.5 | H76: 0.5 | I76: 0.5 | J76: .. | K76: .. | L76: .. | M76: .. | N76: .. | O76: .. | P76: .. | Q76: .. | R76: .. | S76: .. | T76: ..
A77: United Kingdom | B77: GBR | C77: Official exchange rate (LCU per US$, period average) | D77: PA.NUS.FCRF | E77: 0.64717935 | F77: 0.62414084 | G77: 0.63304699 | H77: 0.63966058 | I77: 0.60772963 | J77: 0.65454548 | K77: 0.74063446 | L77: 0.77697668 | M77: 0.74953154 | N77: 0.78344511 | O77: 0.77999958 | P77: 0.72706494 | Q77: 0.81130172 | R77: 0.80453891 | S77: 0.78241458 | T77: 0.75947396
A78: United Kingdom | B78: GBR | C78: Exports of goods and services (% of GDP) | D78: NE.EXP.GNFS.ZS | E78: 28.746366 | F78: 31.264922 | G78: 30.499539 | H78: 30.207616 | I78: 28.532009 | J78: 27.879074 | K78: 29.061556 | L78: 30.973831 | M78: 31.854534 | N78: 31.90286 | O78: 29.948652 | P78: 29.289407 | Q78: 34.061928 | R78: 31.91227 | S78: 31.056144 | T78: 30.596958
A79: United Kingdom | B79: GBR | C79: Imports of goods and services (% of GDP) | D79: NE.IMP.GNFS.ZS | E79: 30.304814 | F79: 32.05914 | G79: 31.469332 | H79: 31.511924 | I79: 30.289014 | J79: 29.245971 | K79: 30.777975 | L79: 32.216093 | M79: 33.055238 | N79: 33.100706 | O79: 29.211237 | P79: 29.248979 | Q79: 35.136998 | R79: 33.080114 | S79: 31.782908 | T79: 31.860371
A80: United Kingdom | B80: GBR | C80: Foreign direct investment, net inflows (BoP, current US$) | D80: BX.KLT.DINV.CD.WD | E80: 6.6734551e+10 | F80: 2.701205e+10 | G80: 4.675079e+10 | H80: 5.4473175e+10 | I80: 5.8890445e+10 | J80: 4.5333483e+10 | K80: 3.2481322e+11 | L80: 1.2535881e+11 | M80: -2.505544e+10 | N80: 1.9790762e+10 | O80: 1.5718556e+11 | P80: 1.0243156e+11 | Q80: 9.2776358e+10 | R80: 1.3789804e+10 | S80: -1.2955141e+10 | T80: 7.6628405e+10
A81: United Kingdom | B81: GBR | C81: Population, total | D81: SP.POP.TOTL | E81: 62766365 | F81: 63258810 | G81: 63711000 | H81: 64138000 | I81: 64619000 | J81: 65087000 | K81: 65606000 | L81: 65964000 | M81: 66287000 | N81: 66628000 | O81: 66740000 | P81: 66978000 | Q81: 67636000 | R81: 68526000 | S81: 69281000 | T81: 69487000
A82: United States | B82: USA | C82: GDP (current US$) | D82: NY.GDP.MKTP.CD | E82: 15048971000000 | F82: 15599732000000 | G82: 16253970000000 | H82: 16880683000000 | I82: 17608138000000 | J82: 18295019000000 | K82: 18804913000000 | L82: 19612102000000 | M82: 20656516000000 | N82: 21539982000000 | O82: 21375281000000 | P82: 23725645000000 | Q82: 26054614000000 | R82: 27811517000000 | S82: 29298013000000 | T82: 30769700000000
A83: United States | B83: USA | C83: GDP growth (annual %) | D83: NY.GDP.MKTP.KD.ZG | E83: 2.6951926 | F83: 1.5644069 | G83: 2.2891134 | H83: 2.1178301 | I83: 2.5238198 | J83: 2.9455505 | K83: 1.8194515 | L83: 2.4576223 | M83: 2.9665051 | N83: 2.5838253 | O83: -2.081376 | P83: 6.1520225 | Q83: 2.5242139 | R83: 2.9343632 | S83: 2.7931872 | T83: 2.161382
A84: United States | B84: USA | C84: Inflation, consumer prices (annual %) | D84: FP.CPI.TOTL.ZG | E84: 1.6400434 | F84: 3.1568416 | G84: 2.0693373 | H84: 1.4648327 | I84: 1.622223 | J84: 0.11862714 | K84: 1.2615832 | L84: 2.13011 | M84: 2.4425833 | N84: 1.8122101 | O84: 1.2335844 | P84: 4.6978589 | Q84: 8.0027998 | R84: 4.1163384 | S84: 2.9495252 | T84: ..
A85: United States | B85: USA | C85: Unemployment, total (% of total labor force) (modeled ILO estimate) | D85: SL.UEM.TOTL.ZS | E85: 9.633 | F85: 8.949 | G85: 8.069 | H85: 7.375 | I85: 6.168 | J85: 5.28 | K85: 4.869 | L85: 4.355 | M85: 3.896 | N85: 3.669 | O85: 8.055 | P85: 5.349 | Q85: 3.65 | R85: 3.638 | S85: 4.022 | T85: 4.198
A86: United States | B86: USA | C86: Lending interest rate (%) | D86: FR.INR.LEND | E86: 3.25 | F86: 3.25 | G86: 3.25 | H86: 3.25 | I86: 3.25 | J86: 3.26 | K86: 3.5116667 | L86: 4.0966667 | M86: 4.9041667 | N86: 5.2825 | O86: 3.5441667 | P86: 3.25 | Q86: .. | R86: .. | S86: .. | T86: ..
A87: United States | B87: USA | C87: Official exchange rate (LCU per US$, period average) | D87: PA.NUS.FCRF | E87: 1 | F87: 1 | G87: 1 | H87: 1 | I87: 1 | J87: 1 | K87: 1 | L87: 1 | M87: 1 | N87: 1 | O87: 1 | P87: 1 | Q87: 1 | R87: 1 | S87: 1 | T87: 1
A88: United States | B88: USA | C88: Exports of goods and services (% of GDP) | D88: NE.EXP.GNFS.ZS | E88: 12.341355 | F88: 13.563464 | G88: 13.644051 | H88: 13.553492 | I88: 13.508214 | J88: 12.411149 | K88: 11.888159 | L88: 12.177481 | M88: 12.287111 | N88: 11.789197 | O88: 10.123081 | P88: 10.826669 | Q88: 11.654097 | R88: 11.050674 | S88: 10.974696 | T88: ..
A89: United States | B89: USA | C89: Imports of goods and services (% of GDP) | D89: NE.IMP.GNFS.ZS | E89: 15.878528 | F89: 17.279015 | G89: 17.037788 | H89: 16.387814 | I89: 16.398355 | J89: 15.277065 | K89: 14.564439 | L89: 14.947857 | M89: 15.158248 | N89: 14.469283 | O89: 13.016863 | P89: 14.406057 | Q89: 15.253801 | R89: 13.878624 | S89: 14.041321 | T89: ..
A90: United States | B90: USA | C90: Foreign direct investment, net inflows (BoP, current US$) | D90: BX.KLT.DINV.CD.WD | E90: 264039000000 | F90: 263497000000 | G90: 250345000000 | H90: 288131000000 | I90: 251856000000 | J90: 511434000000 | K90: 474388000000 | L90: 380823000000 | M90: 214715000000 | N90: 315984000000 | O90: 137066000000 | P90: 477956000000 | Q90: 416890000000 | R90: 361944000000 | S90: 297058000000 | T90: 400519000000
A91: United States | B91: USA | C91: Population, total | D91: SP.POP.TOTL | E91: 309378227 | F91: 311839461 | G91: 314339099 | H91: 316726282 | I91: 319257560 | J91: 321815121 | K91: 324353340 | L91: 326608609 | M91: 328529577 | N91: 330226227 | O91: 331578104 | P91: 332100166 | Q91: 333996304 | R91: 336755052 | S91: 340003797 | T91: 341784857
A92: Australia | B92: AUS | C92: GDP (current US$) | D92: NY.GDP.MKTP.CD | E92: 1.1525666e+12 | F92: 1.4029399e+12 | G92: 1.5527284e+12 | H92: 1.5837375e+12 | I92: 1.474677e+12 | J92: 1.3568058e+12 | K92: 1.2115881e+12 | L92: 1.3308906e+12 | M92: 1.433145e+12 | N92: 1.3983496e+12 | O92: 1.3333365e+12 | P92: 1.5606175e+12 | Q92: 1.6956275e+12 | R92: 1.7344513e+12 | S92: 1.7570225e+12 | T92: 1.7985189e+12
A93: Australia | B93: AUS | C93: GDP growth (annual %) | D93: NY.GDP.MKTP.KD.ZG | E93: 2.210048 | F93: 2.3947349 | G93: 3.9524714 | H93: 2.654453 | I93: 2.6011898 | J93: 2.1643478 | K93: 2.7556407 | L93: 2.2933103 | M93: 2.8741704 | N93: 2.194017 | O93: -0.1335319 | P93: 2.0069484 | Q93: 4.2530456 | R93: 3.583821 | S93: 1.3734077 | T93: 1.3503979
A94: Australia | B94: AUS | C94: Inflation, consumer prices (annual %) | D94: FP.CPI.TOTL.ZG | E94: 2.918337 | F94: 3.3038478 | G94: 1.762783 | H94: 2.4498825 | I94: 2.4879293 | J94: 1.508368 | K94: 1.2769937 | L94: 1.9486431 | M94: 1.9114 | N94: 1.6107709 | O94: 0.84690073 | P94: 2.8639128 | Q94: 6.5940966 | R94: 5.5970179 | S94: 3.1665667 | T94: 2.8740379
A95: Australia | B95: AUS | C95: Unemployment, total (% of total labor force) (modeled ILO estimate) | D95: SL.UEM.TOTL.ZS | E95: 5.214 | F95: 5.083 | G95: 5.225 | H95: 5.663 | I95: 6.078 | J95: 6.055 | K95: 5.711 | L95: 5.592 | M95: 5.345 | N95: 5.143 | O95: 6.394 | P95: 5.022 | Q95: 3.728 | R95: 3.668 | S95: 3.942 | T95: 4.09
A96: Australia | B96: AUS | C96: Lending interest rate (%) | D96: FR.INR.LEND | E96: 7.2791667 | F96: 7.7375 | G96: 6.975 | H96: 6.1791667 | I96: 5.95 | J96: 5.575 | K96: 5.4208333 | L96: 5.2455 | M96: 5.2608333 | N96: 5.101 | O96: .. | P96: .. | Q96: .. | R96: .. | S96: .. | T96: ..
A97: Australia | B97: AUS | C97: Official exchange rate (LCU per US$, period average) | D97: PA.NUS.FCRF | E97: 1.0901595 | F97: 0.9694632 | G97: 0.96580103 | H97: 1.0358431 | I97: 1.1093633 | J97: 1.3310903 | K97: 1.345214 | L97: 1.3047581 | M97: 1.3384121 | N97: 1.4385065 | O97: 1.4530851 | P97: 1.3312243 | Q97: 1.4416645 | R97: 1.5051911 | S97: 1.515358 | T97: 1.5519979
A98: Australia | B98: AUS | C98: Exports of goods and services (% of GDP) | D98: NE.EXP.GNFS.ZS | E98: 19.732224 | F98: 21.371095 | G98: 21.421233 | H98: 19.893141 | I98: 20.995918 | J98: 19.984645 | K98: 19.203144 | L98: 21.171841 | M98: 21.812574 | N98: 24.06248 | O98: 23.938037 | P98: 22.001814 | Q98: 25.46153 | R98: 26.701068 | S98: 24.621524 | T98: 23.244438
A99: Australia | B99: AUS | C99: Imports of goods and services (% of GDP) | D99: NE.IMP.GNFS.ZS | E99: 20.658283 | F99: 20.350891 | G99: 21.598617 | H99: 21.207371 | I99: 21.303392 | J99: 21.510105 | K99: 21.610258 | L99: 20.863572 | M99: 21.760652 | N99: 21.939203 | O99: 20.561527 | P99: 18.200422 | Q99: 20.233112 | R99: 22.343271 | S99: 22.523857 | T99: 22.657011
A100: Australia | B100: AUS | C100: Foreign direct investment, net inflows (BoP, current US$) | D100: BX.KLT.DINV.CD.WD | E100: 3.5554699e+10 | F100: 6.5578267e+10 | G100: 5.7571286e+10 | H100: 5.4472699e+10 | I100: 6.3204516e+10 | J100: 4.6892809e+10 | K100: 4.2970226e+10 | L100: 4.8199372e+10 | M100: 6.068664e+10 | N100: 3.874513e+10 | O100: 1.7976844e+10 | P100: 3.145306e+10 | Q100: 6.870942e+10 | R100: 3.5315978e+10 | S100: 5.3722899e+10 | T100: 3.6521352e+10
A101: Australia | B101: AUS | C101: Population, total | D101: SP.POP.TOTL | E101: 22031750 | F101: 22340024 | G101: 22733465 | H101: 23128129 | I101: 23475686 | J101: 23815995 | K101: 24190907 | L101: 24592588 | M101: 24963258 | N101: 25334826 | O101: 25649248 | P101: 25685412 | Q101: 26018721 | R101: 26659922 | S101: 27194286 | T101: 27614411
A105: Data from database: World Development Indicators
A106: Last Updated: 07/13/2026

Sheet Series - Metadata
A1: Code | B1: License Type | C1: Indicator Name | D1: Long definition | E1: Source | F1: Topic | G1: Dataset | H1: Unit of measure | I1: Periodicity | J1: Reference period | K1: Aggregation method | L1: Statistical concept and methodology | M1: Development relevance | N1: Limitations and exceptions | O1: Other notes | P1: License URL
A2: NY.GDP.MKTP.CD | B2: CC BY-4.0 | C2: GDP (current US$) | D2: Gross domestic product is the total income earned through the production of goods and services in an economic territory during an accounting period. It can be measured in three different ways: using either the expenditure approach, the income approach, or the production approach. This indicator is expressed in current prices, meaning no adjustment has been made to account for price changes over time. This indicator is expressed in United States dollars. | E2: Country official statistics, National Statistical Organizations and/or Central Banks; National Accounts data files, Organisation for Economic Co-operation and Development (OECD); Staff estimates, World Bank (WB) | F2: Economic Policy & Debt: National accounts: US$ at current prices: Aggregate indicators | G2: WB_WDI | H2: current US$ | I2: Annual | J2: 1960-2025 | K2: Gap-filled total | L2: Methodology: National accounts are compiled in accordance with international standards: System of National Accounts, 2008 or 1993 versions. Specific information on how countries compile their national accounts can be found on the IMF website: https://dsbb.imf.org/ Statistical concept(s): The conceptual elements of the SNA (System of National Accounts) measure what takes place in the economy, between which agents, and for what purpose. At the heart of the SNA is the production of goods and services. These may be used for consumption in the period to which the accounts relate or may be accumulated for use in a later period. In simple terms, the amount of value added generated by production represents GDP. The income corresponding to GDP is distributed to the various agents or groups of agents as income and it is the process of distributing and redistributing income that allows one agent to consume the goods and services produced by another agent or to acquire goods and services for later consumption. The way in which the SNA captures this pattern of economic flows is to identify the activities concerned by recognizing the institutional units in the economy and by specifying the structure of accounts capturing the transactions relevant to one stage or another of the process by which goods and services are produced and ultimately consumed. | M2: This indicator is related to the national accounts, which are critical for understanding and managing a country's economy. They provide a framework for the analysis of economic performance. National accounts are the basis for estimating the Gross Domestic Product (GDP) and Gross National Income (GNI), which are the most widely used indicator of economic performance. They are essential for government policymakers, providing the data needed to design and assess fiscal and monetary policies; and are also used by businesses and investors to assess the economic climate and make investment decisions. NAS enable comparison between economies, which is crucial for international trade, investment decisions, and economic competitiveness. More specifically, this indicator is related to national accounts aggregates. Gross Domestic Product (GDP), Gross National Income (GNI), and other aggregates provide a snapshot of the size and health of an economy by measuring the total economic activity within a country. They can thus be used by policymakers to design and implement economic policies, as they reflect the overall economic performance and can indicate the need for intervention in certain areas. Aggregates also allow for comparisons between different economies, which can be useful for trade negotiations, investment decisions, and economic benchmarking. By examining aggregates over time, economists and analysts can identify trends, cycles, and potential areas of concern within an economy, and investors can use national accounts aggregates to assess the potential risks and returns of investing in a particular country. Overall, national accounts aggregates are fundamental tools for economic analysis, policy formulation, and decision-making at both the national and international levels. | N2: Gross domestic product (GDP), though widely tracked, may not always be the most relevant summary of aggregated economic performance for all economies, especially when production occurs at the expense of consuming capital stock. While GDP estimates based on the production approach are generally more reliable than estimates compiled from the income or expenditure side, different countries use different definitions, methods, and reporting standards. World Bank staff review the quality of national accounts data and sometimes make adjustments to improve consistency with international guidelines. Nevertheless, significant discrepancies remain between international standards and actual practice. Many statistical offices, especially those in developing countries, face severe limitations in the resources, time, training, and budgets required to produce reliable and comprehensive series of national accounts statistics. Among the difficulties faced by compilers of national accounts is the extent of unreported economic activity in the informal or secondary economy. In developing countries a large share of agricultural output is either not exchanged (because it is consumed within the household) or not exchanged for money. | P2: https://datacatalog.worldbank.org/int/public-licenses#cc-by
A3: NY.GDP.MKTP.KD.ZG | B3: CC BY-4.0 | C3: GDP (annual % growth) | D3: Gross domestic product is the total income earned through the production of goods and services in an economic territory during an accounting period. It can be measured in three different ways: using either the expenditure approach, the income approach, or the production approach. This indicator denotes the percentage change over each previous year of the constant price (base year 2015) series in United States dollars. | E3: Country official statistics, National Statistical Organizations and/or Central Banks; National Accounts data files, Organisation for Economic Co-operation and Development (OECD); Staff estimates, World Bank (WB) | F3: Economic Policy & Debt: National accounts: Growth rates | G3: WB_WDI | H3: % | I3: Annual | J3: 1961-2025 | K3: Weighted average | L3: Methodology: National accounts are compiled in accordance with international standards: System of National Accounts, 2008 or 1993 versions. Specific information on how countries compile their national accounts can be found on the IMF website: https://dsbb.imf.org/ Statistical concept(s): The conceptual elements of the SNA (System of National Accounts) measure what takes place in the economy, between which agents, and for what purpose. At the heart of the SNA is the production of goods and services. These may be used for consumption in the period to which the accounts relate or may be accumulated for use in a later period. In simple terms, the amount of value added generated by production represents GDP. The income corresponding to GDP is distributed to the various agents or groups of agents as income and it is the process of distributing and redistributing income that allows one agent to consume the goods and services produced by another agent or to acquire goods and services for later consumption. The way in which the SNA captures this pattern of economic flows is to identify the activities concerned by recognizing the institutional units in the economy and by specifying the structure of accounts capturing the transactions relevant to one stage or another of the process by which goods and services are produced and ultimately consumed. | M3: This indicator is related to the national accounts, which are critical for understanding and managing a country's economy. They provide a framework for the analysis of economic performance. National accounts are the basis for estimating the Gross Domestic Product (GDP) and Gross National Income (GNI), which are the most widely used indicator of economic performance. They are essential for government policymakers, providing the data needed to design and assess fiscal and monetary policies; and are also used by businesses and investors to assess the economic climate and make investment decisions. NAS enable comparison between economies, which is crucial for international trade, investment decisions, and economic competitiveness. More specifically, this indicator is related to national accounts aggregates. Gross Domestic Product (GDP), Gross National Income (GNI), and other aggregates provide a snapshot of the size and health of an economy by measuring the total economic activity within a country. They can thus be used by policymakers to design and implement economic policies, as they reflect the overall economic performance and can indicate the need for intervention in certain areas. Aggregates also allow for comparisons between different economies, which can be useful for trade negotiations, investment decisions, and economic benchmarking. By examining aggregates over time, economists and analysts can identify trends, cycles, and potential areas of concern within an economy, and investors can use national accounts aggregates to assess the potential risks and returns of investing in a particular country. Overall, national accounts aggregates are fundamental tools for economic analysis, policy formulation, and decision-making at both the national and international levels. | N3: Each industry's contribution to growth in the economy's output is measured by growth in the industry's value added. In principle, value added in constant prices can be estimated by measuring the quantity of goods and services produced in a period, valuing them at an agreed set of base year prices, and subtracting the cost of intermediate inputs, also in constant prices. This double-deflation method requires detailed information on the structure of prices of inputs and outputs. In many industries, however, value added is extrapolated from the base year using single volume indexes of outputs or, less commonly, inputs. Particularly in the services industries, including most of government, value added in constant prices is often imputed from labor inputs, such as real wages or number of employees. In the absence of well defined measures of output, measuring the growth of services remains difficult. Moreover, technical progress can lead to improvements in production processes and in the quality of goods and services that, if not properly accounted for, can distort measures of value added and thus of growth. When inputs are used to estimate output, as for nonmarket services, unmeasured technical progress leads to underestimates of the volume of output. Similarly, unmeasured improvements in quality lead to underestimates of the value of output and value added. The result can be underestimates of growth and productivity improvement and overestimates of inflation. Informal economic activities pose a particular measurement problem, especially in developing countries, where much economic activity is unrecorded. A complete picture of the economy requires estimating household outputs produced for home use, sales in informal markets, barter exchanges, and illicit or deliberately unreported activities. The consistency and completeness of such estimates depend on the skill and methods of the compiling statisticians. Rebasing of national accounts can alter the measured growth rate of an economy and lead to breaks in series that affect the consistency of data over time. When countries rebase their national accounts, they update the weights assigned to various components to better reflect current patterns of production or uses of output. The new base year should represent normal operation of the economy - it should be a year without major shocks or distortions. Some developing countries have not rebased their national accounts for many years. Using an old base year can be misleading because implicit price and volume weights become progressively less relevant and useful. To obtain comparable series of constant price data for computing aggregates, the World Bank rescales GDP and value added by industrial origin to a common reference year. Because rescaling changes the implicit weights used in forming regional and income group aggregates, aggregate growth rates are not comparable with those from earlier editions with different base years. Rescaling may result in a discrepancy between the rescaled GDP and the sum of the rescaled components. To avoid distortions in the growth rates, the discrepancy is left unallocated. As a result, the weighted average of the growth rates of the components generally does not equal the GDP growth rate. | P3: https://datacatalog.worldbank.org/int/public-licenses#cc-by
A4: FP.CPI.TOTL.ZG | B4: CC BY-4.0 | C4: Inflation, consumer prices (annual % growth) | D4: Inflation as measured by the consumer price index reflects the annual percentage change in the cost to the average consumer of acquiring a basket of goods and services that may be fixed or changed at specified intervals, such as yearly. | E4: International Financial Statistics database, International Monetary Fund (IMF) | F4: Financial Sector: Exchange rates & prices | G4: WB_WDI | H4: % | I4: Annual | J4: 1960-2025 | K4: Median | L4: Methodology: Consumer Prices Indices are compiled in accordance with international standards: Consumer Price Index Manual, 2020 or 2004 version. Specific information on how countries compile their CPI statistics can be found on the IMF website: https://dsbb.imf.org/ Statistical concept(s): The conceptual basis of a consumer price index series is to measure the rate at which prices of consumption goods and services are changing from one period to another. | M4: A general and continuing increase in an economy’s price level is called inflation. The increase in the average prices of goods and services in the economy should be distinguished from a change in the relative prices of individual goods and services. Generally accompanying an overall increase in the price level is a change in the structure of relative prices, but it is only the average increase, not the relative price changes, that constitutes inflation. A commonly used measure of inflation is the consumer price index, which measures the prices of a representative basket of goods and services purchased by a typical household. The consumer price index is usually calculated on the basis of periodic surveys of consumer prices. Other price indices are derived implicitly from indexes of current and constant price series. | P4: https://datacatalog.worldbank.org/int/public-licenses#cc-by
A5: SL.UEM.TOTL.ZS | B5: CC BY-4.0 | C5: Unemployment, total (% of total labor force) (modeled ILO estimate) | D5: Unemployment refers to the share of the labor force that is without work but available for and seeking employment. | E5: ILO Modelled Estimates database (ILOEST), International Labour Organization (ILO), uri: https://ilostat.ilo.org/data/bulk/, publisher: ILOSTAT, type: external database, date accessed: January 17, 2026 | F5: Social Protection & Labor: Unemployment | G5: WB_WDI | H5: % of total labor force | I5: Annual | J5: 1991-2025 | K5: Weighted average | L5: Methodology: The unemployment rate is calculated by expressing the number of unemployed persons as a percentage of the total number of persons in the labor force. The labor force (formerly known as the economically active population) is the sum of the number of persons employed and the number of persons unemployed. The series is part of the "ILO modeled estimates database," including nationally reported observations and imputed data for countries with missing data, primarily to capture regional and global trends with consistent country coverage. Country-reported microdata is based mainly on nationally representative labor force surveys, with other sources (e.g., household surveys and population censuses) considering differences in the data source, the scope of coverage, methodology, and other country-specific factors. Country analysis requires caution where limited nationally reported data are available. A series of models are also applied to impute missing observations and make projections. However, imputed observations are not based on national data, are subject to high uncertainty, and should not be used for country comparisons or rankings. For more information: https://ilostat.ilo.org/resources/concepts-and-definitions/ilo-modelled-estimates/ Statistical concept(s): The unemployed comprise all persons of working age who were: a) without work during the reference period, i.e. were not in paid employment or self-employment; b) currently available for work, i.e. were available for paid employment or self-employment during the reference period; and c) seeking work, i.e. had taken specific steps in a specified recent period to seek paid employment or self-employment. Future starters, that is, persons who did not look for work but have a future labor market stake (made arrangements for a future job start) are also counted as unemployed, as are participants in skills training or retraining schemes within employment promotion programs, who on that basis, were “not in employment”, not “currently available” and did not “seek employment” because they had a job offer to start within a short subsequent period generally not greater than three months. The unemployed also include persons “not in employment” who carried out activities to migrate abroad in order to work for pay or profit but who were still waiting for the opportunity to leave. Employment comprises all persons of working age who during a specified brief period, such as one week or one day, were in the following categories: a) paid employment (whether at work or with a job but not at work); or b) self-employment (whether at work or with an enterprise but not at work). The working-age population is the population above the legal working age, but for statistical purposes it comprises all persons above a specified minimum age threshold for which an inquiry on economic activity is made. To promote international comparability, the working-age population is often defined as all persons aged 15 and older, but this may vary from country to country based on national laws and practices (some countries also apply an upper age limit). | M5: The unemployment rate is a useful measure of the underutilization of the labor supply. It reflects the inability of an economy to generate employment for those persons who want to work but are not doing so, even though they are available for employment and actively seeking work. It is thus seen as an indicator of the efficiency and effectiveness of an economy to absorb its labor force and of the performance of the labor market. Given its usefulness in conveying valuable information on a country’s labor market situation and the fact that it is widely recognized as a headline labor market indicator, it was included as one of the indicators to measure progress towards the achievement of the Sustainable Development Goals (SDG), under Goal 8 (Promote sustained, inclusive and sustainable economic growth, full and productive employment and decent work for all). | N5: While the unemployment rate may be considered the most informative labour market indicator, reflecting the general performance of the labour market and the economy as a whole, it should not be interpreted as a measure of economic hardship or of well-being. When based on the internationally-recommended standards, the unemployment rate simply reflects the proportion of the labour force that does not have a job but is available and actively looking for work. It says nothing about the economic resources of unemployed workers or their family members. Its use should, therefore, be limited to serving as a measurement of the utilization of labour and an indication of the failure to find work. Other measures, including income-related indicators, would be needed to evaluate economic hardship. An additional criticism of the aggregate unemployment measure is that it masks information on the composition of the jobless population and therefore misses out on the particularities of the education level, ethnic origin, socio-economic background, work experience, etc. of the unemployed. Moreover, the unemployment rate says nothing about the type of unemployment – whether it is cyclical and short-term or structural and long-term – which is a critical issue for policy makers in the development of their policy responses, especially given that structural unemployment cannot be addressed by boosting market demand only. | O5: National estimates are also available in the WDI database. Caution should be used when comparing ILO estimates with national estimates. | P5: https://datacatalog.worldbank.org/int/public-licenses#cc-by
A6: FR.INR.LEND | B6: CC BY-4.0 | C6: Lending interest rate (%) | D6: Lending rate is the bank rate that usually meets the short- and medium-term financing needs of the private sector. This rate is normally differentiated according to creditworthiness of borrowers and objectives of financing. The terms and conditions attached to these rates differ by country, however, limiting their comparability. | E6: International Financial Statistics database, International Monetary Fund (IMF) | F6: Financial Sector: Interest rates | G6: WB_WDI | H6: % | I6: Annual | J6: 1960-2025 | L6: Methodology: Monetary and Financial statistics are compiled in accordance with international standards: Monetary and Financial Statistics Manual, 2018 or 2004 versions. Specific information on how countries compile their Monetary and Finance statistics can be found on the IMF website: https://dsbb.imf.org/ Statistical concept(s): The conceptual framework comes from the Monetary and Financial Statistic Manual which outlines the analytical presentation of monetary statistics, which provide critical inputs for monetary policy formulation and monitoring. The statistics covered in this Manual also support the assessment of financial system stability. | M6: Both banking and financial systems enhance growth, the main factor in poverty reduction. At low levels of economic development commercial banks tend to dominate the financial system, while at higher levels domestic stock markets tend to become more active and efficient. The size and mobility of international capital flows make it increasingly important to monitor the strength of financial systems. Robust financial systems can increase economic activity and welfare, but instability can disrupt financial activity and impose widespread costs on the economy. | N6: Countries use a variety of reporting formats, sample designs, interest compounding formulas, averaging methods, and data presentations for indices and other data series on interest rates. The IMF's Monetary and Financial Statistics Manual does not provide guidelines beyond the general recommendation that such data should reflect market prices and effective (rather than nominal) interest rates and should be representative of the financial assets and markets to be covered. For more information, please see http://www.imf.org/external/pubs/ft/mfs/manual/index.htm. | P6: https://datacatalog.worldbank.org/int/public-licenses#cc-by
A7: PA.NUS.FCRF | B7: CC BY-4.0 | C7: Official exchange rate (LCU per US$, period average) | D7: Official exchange rate refers to the exchange rate determined by national authorities or to the rate determined in the legally sanctioned exchange market. This indicator represents the ratio of Local Currency Units relative to United States dollars.This indicator is derived as an average over the reference period. | E7: International Financial Statistics database, International Monetary Fund (IMF) | F7: Financial Sector: Exchange rates & prices | G7: WB_WDI | H7: LCU per US$ | I7: Annual | J7: 1960-2025 | L7: Methodology: The exchange rate is the price of one currency divided by another. Official exchange rates and exchange rate arrangements are established by governments. Other exchange rates recognized by governments include market rates, which are determined largely by legal market forces, and for countries with multiple exchange arrangements, principal rates, secondary rates, and tertiary rates. Annual average exchange rates are derived as the simple average of daily exchange rates for a specified calendar year Statistical concept(s): The exchange rate is the price of one currency in terms of another. Official exchange rates and exchange rate arrangements are established by governments. Other exchange rates recognized by governments include market rates, which are determined largely by legal market forces, and for countries with multiple exchange arrangements, principal rates, secondary rates, and tertiary rates. | M7: In a market-based economy, household, producer, and government choices about resource allocation are influenced by relative prices, including the real exchange rate, real wages, real interest rates, and other prices in the economy. Relative prices also largely reflect these agents' choices. Thus relative prices convey vital information about the interaction of economic agents in an economy and with the rest of the world. | N7: Official or market exchange rates are often used to convert economic statistics in local currencies to a common currency in order to make comparisons across countries. Since market rates reflect at best the relative prices of tradable goods, the volume of goods and services that a U.S. dollar buys in the United States may not correspond to what a U.S. dollar converted to another country's currency at the official exchange rate would buy in that country, particularly when nontradable goods and services account for a significant share of a country's output. An alternative exchange rate - the purchasing power parity (PPP) conversion factor - is preferred because it reflects differences in price levels for both tradable and nontradable goods and services and therefore provides a more meaningful comparison of real output. | P7: https://datacatalog.worldbank.org/int/public-licenses#cc-by
A8: NE.EXP.GNFS.ZS | B8: CC BY-4.0 | C8: Exports of goods and services (% of GDP) | D8: Exports of goods includes changes in the economic ownership of goods from residents of the compiling economy to non-residents, irrespective of physical movement of goods across national borders. Exports of services includes services provided by residents to non-residents. This indicator is expressed as a percentage of Gross Domestic Product (GDP) which is the total income earned through the production of goods and services in an economic territory during an accounting period. | E8: Country official statistics, National Statistical Offices (NSOs); National Accounts data files, Central Banks; Staff estimates, World Bank (WB) | F8: Economic Policy & Debt: National accounts: Shares of GDP & other | G8: WB_WDI | H8: % | I8: Annual | J8: 1960-2025 | K8: Weighted average | L8: Methodology: National accounts are compiled in accordance with international standards: System of National Accounts, 2008 or 1993 versions. Specific information on how countries compile their national accounts can be found on the IMF website: https://dsbb.imf.org/ Statistical concept(s): The conceptual elements of the SNA (System of National Accounts) measure what takes place in the economy, between which agents, and for what purpose. At the heart of the SNA is the production of goods and services. These may be used for consumption in the period to which the accounts relate or may be accumulated for use in a later period. In simple terms, the amount of value added generated by production represents GDP. The income corresponding to GDP is distributed to the various agents or groups of agents as income and it is the process of distributing and redistributing income that allows one agent to consume the goods and services produced by another agent or to acquire goods and services for later consumption. The way in which the SNA captures this pattern of economic flows is to identify the activities concerned by recognizing the institutional units in the economy and by specifying the structure of accounts capturing the transactions relevant to one stage or another of the process by which goods and services are produced and ultimately consumed. | M8: This indicator is related to the national accounts, which are critical for understanding and managing a country's economy. They provide a framework for the analysis of economic performance. National accounts are the basis for estimating the Gross Domestic Product (GDP) and Gross National Income (GNI), which are the most widely used indicators of economic performance. They are essential for government policymakers, providing the data needed to design and assess fiscal and monetary policies; and are also used by businesses and investors to assess the economic climate and make investment decisions. NAS enable comparison between economies, which is crucial for international trade, investment decisions, and economic competitiveness. More specifically, this indicator is related to the expenditure approach used to calculate GDP, which focuses on the total amount of spending on final goods and services within an economy over a specific period. Unlike the production approach, which looks at the supply side by summing the value of output produced by all sectors, the expenditure approach looks at the demand side by summing all expenditures. This demand-side analysis provides insights into the spending behaviors of different sectors, including households, businesses, the government, and foreign entities. Also, by breaking down expenditures into categories like consumption, investment, government spending, and net exports, it helps identify which components are driving or hindering economic growth. This approach can thus be used to assess the effectiveness of fiscal and monetary policies. Overall, the expenditure approach is crucial for understanding the dynamics of an economy, guiding policy decisions, and providing a comprehensive view of economic activity from the perspective of total spending. | N8: Because policymakers have tended to focus on fostering the growth of output, and because data on production are easier to collect than data on spending, many countries generate their primary estimate of GDP using the production approach. Moreover, many countries do not estimate all the components of national expenditures but instead derive some of the main aggregates indirectly using GDP (based on the production approach) as the control total. Data on exports and imports are compiled from customs reports and balance of payments data. Although the data from the payments side provide reasonably reliable records of cross-border transactions, they may not adhere strictly to the appropriate definitions of valuation and timing used in the balance of payments or correspond to the change-of ownership criterion. This issue has assumed greater significance with the increasing globalization of international business. Neither customs nor balance of payments data usually capture the illegal transactions that occur in many countries. Goods carried by travelers across borders in legal but unreported shuttle trade may further distort trade statistics. | P8: https://datacatalog.worldbank.org/int/public-licenses#cc-by
A9: NE.IMP.GNFS.ZS | B9: CC BY-4.0 | C9: Imports of goods and services (% of GDP) | D9: Imports of goods includes change in the economic ownership of goods from non-residents to residents of the compiling economy, irrespective of physical movement of goods across national borders. Imports of services includes services provided by non-residents to residents. This indicator is expressed as a percentage of Gross Domestic Product (GDP) which is the total income earned through the production of goods and services in an economic territory during an accounting period. | E9: Country official statistics, National Statistical Offices (NSOs); National Accounts data files, Central Banks; Staff estimates, World Bank (WB) | F9: Economic Policy & Debt: National accounts: Shares of GDP & other | G9: WB_WDI | H9: % | I9: Annual | J9: 1960-2025 | K9: Weighted average | L9: Methodology: National accounts are compiled in accordance with international standards: System of National Accounts, 2008 or 1993 versions. Specific information on how countries compile their national accounts can be found on the IMF website: https://dsbb.imf.org/ Statistical concept(s): The conceptual elements of the SNA (System of National Accounts) measure what takes place in the economy, between which agents, and for what purpose. At the heart of the SNA is the production of goods and services. These may be used for consumption in the period to which the accounts relate or may be accumulated for use in a later period. In simple terms, the amount of value added generated by production represents GDP. The income corresponding to GDP is distributed to the various agents or groups of agents as income and it is the process of distributing and redistributing income that allows one agent to consume the goods and services produced by another agent or to acquire goods and services for later consumption. The way in which the SNA captures this pattern of economic flows is to identify the activities concerned by recognizing the institutional units in the economy and by specifying the structure of accounts capturing the transactions relevant to one stage or another of the process by which goods and services are produced and ultimately consumed. | M9: This indicator is related to the national accounts, which are critical for understanding and managing a country's economy. They provide a framework for the analysis of economic performance. National accounts are the basis for estimating the Gross Domestic Product (GDP) and Gross National Income (GNI), which are the most widely used indicator of economic performance. They are essential for government policymakers, providing the data needed to design and assess fiscal and monetary policies; and are also used by businesses and investors to assess the economic climate and make investment decisions. NAS enable comparison between economies, which is crucial for international trade, investment decisions, and economic competitiveness. More specifically, this indicator is related to the expenditure approach used to calculate GDP, which focuses on the total amount of spending on final goods and services within an economy over a specific period. Unlike the production approach, which looks at the supply side by summing the value of output produced by all sectors, the expenditure approach looks at the demand side by summing all expenditures. This demand-side analysis provides insights into the spending behaviors of different sectors, including households, businesses, the government, and foreign entities. Also, by breaking down expenditures into categories like consumption, investment, government spending, and net exports, it helps identify which components are driving or hindering economic growth. This approach can thus be used to assess the effectiveness of fiscal and monetary policies. Overall, the expenditure approach is crucial for understanding the dynamics of an economy, guiding policy decisions, and providing a comprehensive view of economic activity from the perspective of total spending. | N9: Because policymakers have tended to focus on fostering the growth of output, and because data on production are easier to collect than data on spending, many countries generate their primary estimate of GDP using the production approach. Moreover, many countries do not estimate all the components of national expenditures but instead derive some of the main aggregates indirectly using GDP (based on the production approach) as the control total. Data on exports and imports are compiled from customs reports and balance of payments data. Although the data from the payments side provide reasonably reliable records of cross-border transactions, they may not adhere strictly to the appropriate definitions of valuation and timing used in the balance of payments or corresponds to the change-of ownership criterion. This issue has assumed greater significance with the increasing globalization of international business. Neither customs nor balance of payments data usually capture the illegal transactions that occur in many countries. Goods carried by travelers across borders in legal but unreported shuttle trade may further distort trade statistics. | P9: https://datacatalog.worldbank.org/int/public-licenses#cc-by
A10: BX.KLT.DINV.CD.WD | B10: CC BY-4.0 | C10: Foreign direct investment, net inflows (BoP, current US$) | D10: Foreign direct investment refers to direct investment equity flows in the reporting economy. It is the sum of equity capital, reinvestment of earnings, and other capital. Direct investment is a category of cross-border investment associated with a resident in one economy having control or a significant degree of influence on the management of an enterprise that is resident in another economy. Ownership of 10 percent or more of the ordinary shares of voting stock is the criterion for determining the existence of a direct investment relationship. Data are in current U.S. dollars. | E10: Balance of Payments database, International Monetary Fund (IMF), note: International Monetary Fund, Balance of Payments database, supplemented by data from the United Nations Conference on Trade and Development and official national sources.; UN Conference on Trade and Development (UNCTAD); Official national sources | F10: Economic Policy & Debt: Balance of payments: Capital & financial account | G10: WB_WDI | I10: Annual | J10: 1970-2025 | K10: Sum | L10: Methodology: Data on equity flows are based on balance of payments data reported by the International Monetary Fund (IMF). Foreign direct investment (FDI) data are supplemented by the World Bank staff estimates using data from the United Nations Conference on Trade and Development (UNCTAD) and official national sources. The internationally accepted definition of FDI (from the sixth edition of the IMF's Balance of Payments Manual [2009]), includes the following components: equity investment, including investment associated with equity that gives rise to control or influence; investment in indirectly influenced or controlled enterprises; investment in fellow enterprises; debt (except selected debt); and reverse investment. The Framework for Direct Investment Relationships provides criteria for determining whether cross-border ownership results in a direct investment relationship, based on control and influence. Distinguished from other kinds of international investment, FDI is made to establish a lasting interest in or effective management control over an enterprise in another country. A lasting interest in an investment enterprise typically involves establishing warehouses, manufacturing facilities, and other permanent or long-term organizations abroad. Direct investments may take the form of greenfield investment, where the investor starts a new venture in a foreign country by constructing new operational facilities; joint venture, where the investor enters into a partnership agreement with a company abroad to establish a new enterprise; or merger and acquisition, where the investor acquires an existing enterprise abroad. The IMF suggests that investments should account for at least 10 percent of voting stock to be counted as FDI. In practice many countries set a higher threshold. Many countries fail to report reinvested earnings, and the definition of long-term loans differs among countries. BoP refers to Balance of Payments. | M10: Private financial flows - equity and debt - account for the bulk of development finance. Equity flows comprise foreign direct investment (FDI) and portfolio equity. Debt flows are financing raised through bond issuance, bank lending, and supplier credits. | N10: FDI data do not give a complete picture of international investment in an economy. Balance of payments data on FDI do not include capital raised locally, an important source of investment financing in some developing countries. In addition, FDI data omit nonequity cross-border transactions such as intra-unit flows of goods and services. The volume of global private financial flows reported by the World Bank generally differs from that reported by other sources because of differences in sources, classification of economies, and method used to adjust and disaggregate reported information. In addition, particularly for debt financing, differences may also reflect how some installments of the transactions and certain offshore issuances are treated. Data on equity flows are shown for all countries for which data are available. | O10: Note: Data starting from 2005 are based on the sixth edition of the IMF's Balance of Payments Manual (BPM6). | P10: https://datacatalog.worldbank.org/int/public-licenses#cc-by
A11: SP.POP.TOTL | B11: CC BY-4.0 | C11: Population, total | D11: Total population is based on the de facto definition of population, which counts all residents regardless of legal status or citizenship. The values shown are midyear estimates. | E11: World Population Prospects, United Nations (UN), uri: https://population.un.org/wpp/, publisher: UN Population Division; Statistical databases and publications from national statistical offices, National Statistical Offices (NSOs), uri: https://unstats.un.org/home/nso_sites/, publisher: National Statistical Offices; Eurostat: Demographic Statistics, Eurostat (ESTAT), uri: https://ec.europa.eu/eurostat/data/database?node_code=earn_ses_monthly, publisher: Eurostat; Population and Vital Statistics Report (various years), United Nations (UN), uri: https://unstats.un.org, publisher: UN Statistics Division | F11: Health: Population: Structure | G11: WB_WDI | H11: Unit | I11: Annual | J11: 1960-2025 | K11: Sum | L11: Methodology: Population estimates are usually based on national population censuses, and estimates of fertility, mortality and migration. Errors and undercounting in census occur even in high-income countries. In developing countries errors may be substantial because of limits in the transport, communications, and other resources required to conduct and analyze a full census. The quality and reliability of official demographic data are also affected by public trust in the government, government commitment to full and accurate enumeration, confidentiality and protection against misuse of census data, and census agencies' independence from political influence. Moreover, comparability of population indicators is limited by differences in the concepts, definitions, collection procedures, and estimation methods used by national statistical agencies and other organizations that collect the data. The currentness of a census and the availability of complementary data from surveys or registration systems are objective ways to judge demographic data quality. Some European countries' registration systems offer complete information on population in the absence of a census. The United Nations Statistics Division monitors the completeness of vital registration systems. Some developing countries have made progress over the last 60 years, but others still have deficiencies in civil registration systems. International migration is the only other factor besides birth and death rates that directly determines a country's population change. Estimating migration is difficult. At any time many people are located outside their home country as tourists, workers, or refugees or for other reasons. Standards for the duration and purpose of international moves that qualify as migration vary, and estimates require information on flows into and out of countries that is difficult to collect. One of the major data sources of this indicator is UN Population Division's World Population Prospects, which use the cohort component method to produce population estimates and projections. Population projections, starting from a base year are projected forward using assumptions of mortality, fertility, and migration by age and sex through 2050, based on the UN Population Division's World Population Prospects database medium variant. Statistical concept(s): Estimates of total population describe the size of total population. Population estimates are dependent on the demographic components of change that are fertility, mortality and migration. As the size of population continues to change throughout the time even within a year, a reference time in the year that the estimate refers to is needed, such as mid-year, end-year or beginning of year. The values shown are midyear estimates. | M11: Increases in human population, whether as a result of immigration or more births than deaths, can impact natural resources and social infrastructure. This can place pressure on a country's sustainability. A significant growth in population will negatively impact the availability of land for agricultural production, and will aggravate demand for food, energy, water, social services, and infrastructure. On the other hand, decreasing population size - a result of fewer births than deaths, and people moving out of a country - can impact a government's commitment to maintain services and infrastructure. | N11: Current population estimates for developing countries that lack (i) reliable recent census data, and (ii) pre- and post-census estimates for countries with census data, are provided by the United Nations Population Division and other agencies. The cohort component method - a standard method for estimating and projecting population - requires fertility, mortality, and net migration data, often collected from sample surveys, which can be small or limited in coverage. Population estimates are from demographic modeling and so are susceptible to biases and errors from shortcomings in both the model and the data. Because future trends cannot be known with certainty, population projections have a wide range of uncertainty. | O11: Relevance to gender indicator: disaggregating the population composition by gender will help a country in projecting its demand for social services on a gender basis. | P11: https://datacatalog.worldbank.org/int/public-licenses#cc-by

Sheet Table1
A1: Country Name | B1: Country Code | C1: Series Name | D1: Series Code | E1: Years | F1: Value | G1: Look Up
A2: Pakistan | B2: PAK | C2: GDP (current US$) | D2: NY.GDP.MKTP.CD | E2: 2010 | F2: 1.9670962e+11 | G2: =Table1_1[[#This Row],[Country Name]]&"|"&Table1_1[[#This Row],[Series Name]]&"|"&Table1_1[[#This Row],[Years]] -> Pakistan|GDP (current US$)|2010
A3: Pakistan | B3: PAK | C3: GDP (current US$) | D3: NY.GDP.MKTP.CD | E3: 2011 | F3: 2.3058658e+11 | G3: =Table1_1[[#This Row],[Country Name]]&"|"&Table1_1[[#This Row],[Series Name]]&"|"&Table1_1[[#This Row],[Years]] -> Pakistan|GDP (current US$)|2011
A4: Pakistan | B4: PAK | C4: GDP (current US$) | D4: NY.GDP.MKTP.CD | E4: 2012 | F4: 2.5010697e+11 | G4: =Table1_1[[#This Row],[Country Name]]&"|"&Table1_1[[#This Row],[Series Name]]&"|"&Table1_1[[#This Row],[Years]] -> Pakistan|GDP (current US$)|2012
A5: Pakistan | B5: PAK | C5: GDP (current US$) | D5: NY.GDP.MKTP.CD | E5: 2013 | F5: 2.5865723e+11 | G5: =Table1_1[[#This Row],[Country Name]]&"|"&Table1_1[[#This Row],[Series Name]]&"|"&Table1_1[[#This Row],[Years]] -> Pakistan|GDP (current US$)|2013
A6: Pakistan | B6: PAK | C6: GDP (current US$) | D6: NY.GDP.MKTP.CD | E6: 2014 | F6: 2.7139047e+11 | G6: =Table1_1[[#This Row],[Country Name]]&"|"&Table1_1[[#This Row],[Series Name]]&"|"&Table1_1[[#This Row],[Years]] -> Pakistan|GDP (current US$)|2014
A7: Pakistan | B7: PAK | C7: GDP (current US$) | D7: NY.GDP.MKTP.CD | E7: 2015 | F7: 2.9996359e+11 | G7: =Table1_1[[#This Row],[Country Name]]&"|"&Table1_1[[#This Row],[Series Name]]&"|"&Table1_1[[#This Row],[Years]] -> Pakistan|GDP (current US$)|2015
A8: Pakistan | B8: PAK | C8: GDP (current US$) | D8: NY.GDP.MKTP.CD | E8: 2016 | F8: 3.1363e+11 | G8: =Table1_1[[#This Row],[Country Name]]&"|"&Table1_1[[#This Row],[Series Name]]&"|"&Table1_1[[#This Row],[Years]] -> Pakistan|GDP (current US$)|2016
A9: Pakistan | B9: PAK | C9: GDP (current US$) | D9: NY.GDP.MKTP.CD | E9: 2017 | F9: 3.3920553e+11 | G9: =Table1_1[[#This Row],[Country Name]]&"|"&Table1_1[[#This Row],[Series Name]]&"|"&Table1_1[[#This Row],[Years]] -> Pakistan|GDP (current US$)|2017
A10: Pakistan | B10: PAK | C10: GDP (current US$) | D10: NY.GDP.MKTP.CD | E10: 2018 | F10: 3.5612817e+11 | G10: =Table1_1[[#This Row],[Country Name]]&"|"&Table1_1[[#This Row],[Series Name]]&"|"&Table1_1[[#This Row],[Years]] -> Pakistan|GDP (current US$)|2018
A11: Pakistan | B11: PAK | C11: GDP (current US$) | D11: NY.GDP.MKTP.CD | E11: 2019 | F11: 3.2090947e+11 | G11: =Table1_1[[#This Row],[Country Name]]&"|"&Table1_1[[#This Row],[Series Name]]&"|"&Table1_1[[#This Row],[Years]] -> Pakistan|GDP (current US$)|2019
A12: Pakistan | B12: PAK | C12: GDP (current US$) | D12: NY.GDP.MKTP.CD | E12: 2020 | F12: 3.0042561e+11 | G12: =Table1_1[[#This Row],[Country Name]]&"|"&Table1_1[[#This Row],[Series Name]]&"|"&Table1_1[[#This Row],[Years]] -> Pakistan|GDP (current US$)|2020
A13: Pakistan | B13: PAK | C13: GDP (current US$) | D13: NY.GDP.MKTP.CD | E13: 2021 | F13: 3.4851665e+11 | G13: =Table1_1[[#This Row],[Country Name]]&"|"&Table1_1[[#This Row],[Series Name]]&"|"&Table1_1[[#This Row],[Years]] -> Pakistan|GDP (current US$)|2021
... A77: Pakistan | B77: PAK | C77: Lending interest rate (%) | D77: FR.INR.LEND | E77: 2021 | F77: 8.6659742 | G77: =Table1_1[[#This Row],[Country Name]]&"|"&Table1_1[[#This Row],[Series Name]]&"|"&Table1_1[[#This Row],[Years]] -> Pakistan|Lending interest rate (%)|2021
A78: Pakistan | B78: PAK | C78: Lending interest rate (%) | D78: FR.INR.LEND | E78: 2022 | G78: =Table1_1[[#This Row],[Country Name]]&"|"&Table1_1[[#This Row],[Series Name]]&"|"&Table1_1[[#This Row],[Years]] -> Pakistan|Lending interest rate (%)|2022
A79: Pakistan | B79: PAK | C79: Lending interest rate (%) | D79: FR.INR.LEND | E79: 2023 | G79: =Table1_1[[#This Row],[Country Name]]&"|"&Table1_1[[#This Row],[Series Name]]&"|"&Table1_1[[#This Row],[Years]] -> Pakistan|Lending interest rate (%)|2023
A80: Pakistan | B80: PAK | C80: Lending interest rate (%) | D80: FR.INR.LEND | E80: 2024 | G80: =Table1_1[[#This Row],[Country Name]]&"|"&Table1_1[[#This Row],[Series Name]]&"|"&Table1_1[[#This Row],[Years]] -> Pakistan|Lending interest rate (%)|2024
A81: Pakistan | B81: PAK | C81: Lending interest rate (%) | D81: FR.INR.LEND | E81: 2025 | G81: =Table1_1[[#This Row],[Country Name]]&"|"&Table1_1[[#This Row],[Series Name]]&"|"&Table1_1[[#This Row],[Years]] -> Pakistan|Lending interest rate (%)|2025
A82: Pakistan | B82: PAK | C82: Official exchange rate (LCU per US$, period average) | D82: PA.NUS.FCRF | E82: 2010 | F82: 85.193816 | G82: =Table1_1[[#This Row],[Country Name]]&"|"&Table1_1[[#This Row],[Series Name]]&"|"&Table1_1[[#This Row],[Years]] -> Pakistan|Official exchange rate (LCU per US$, period average)|2010
A83: Pakistan | B83: PAK | C83: Official exchange rate (LCU per US$, period average) | D83: PA.NUS.FCRF | E83: 2011 | F83: 86.343383 | G83: =Table1_1[[#This Row],[Country Name]]&"|"&Table1_1[[#This Row],[Series Name]]&"|"&Table1_1[[#This Row],[Years]] -> Pakistan|Official exchange rate (LCU per US$, period average)|2011
A84: Pakistan | B84: PAK | C84: Official exchange rate (LCU per US$, period average) | D84: PA.NUS.FCRF | E84: 2012 | F84: 93.395197 | G84: =Table1_1[[#This Row],[Country Name]]&"|"&Table1_1[[#This Row],[Series Name]]&"|"&Table1_1[[#This Row],[Years]] -> Pakistan|Official exchange rate (LCU per US$, period average)|2012
A85: Pakistan | B85: PAK | C85: Official exchange rate (LCU per US$, period average) | D85: PA.NUS.FCRF | E85: 2013 | F85: 101.6289 | G85: =Table1_1[[#This Row],[Country Name]]&"|"&Table1_1[[#This Row],[Series Name]]&"|"&Table1_1[[#This Row],[Years]] -> Pakistan|Official exchange rate (LCU per US$, period average)|2013
A86: Pakistan | B86: PAK | C86: Official exchange rate (LCU per US$, period average) | D86: PA.NUS.FCRF | E86: 2014 | F86: 101.10009 | G86: =Table1_1[[#This Row],[Country Name]]&"|"&Table1_1[[#This Row],[Series Name]]&"|"&Table1_1[[#This Row],[Years]] -> Pakistan|Official exchange rate (LCU per US$, period average)|2014
A87: Pakistan | B87: PAK | C87: Official exchange rate (LCU per US$, period average) | D87: PA.NUS.FCRF | E87: 2015 | F87: 102.76927 | G87: =Table1_1[[#This Row],[Country Name]]&"|"&Table1_1[[#This Row],[Series Name]]&"|"&Table1_1[[#This Row],[Years]] -> Pakistan|Official exchange rate (LCU per US$, period average)|2015
A88: Pakistan | B88: PAK | C88: Official exchange rate (LCU per US$, period average) | D88: PA.NUS.FCRF | E88: 2016 | F88: 104.76912 | G88: =Table1_1[[#This Row],[Country Name]]&"|"&Table1_1[[#This Row],[Series Name]]&"|"&Table1_1[[#This Row],[Years]] -> Pakistan|Official exchange rate (LCU per US$, period average)|2016
A89: Pakistan | B89: PAK | C89: Official exchange rate (LCU per US$, period average) | D89: PA.NUS.FCRF | E89: 2017 | F89: 105.45516 | G89: =Table1_1[[#This Row],[Country Name]]&"|"&Table1_1[[#This Row],[Series Name]]&"|"&Table1_1[[#This Row],[Years]] -> Pakistan|Official exchange rate (LCU per US$, period average)|2017
A90: Pakistan | B90: PAK | C90: Official exchange rate (LCU per US$, period average) | D90: PA.NUS.FCRF | E90: 2018 | F90: 121.82407 | G90: =Table1_1[[#This Row],[Country Name]]&"|"&Table1_1[[#This Row],[Series Name]]&"|"&Table1_1[[#This Row],[Years]] -> Pakistan|Official exchange rate (LCU per US$, period average)|2018
A91: Pakistan | B91: PAK | C91: Official exchange rate (LCU per US$, period average) | D91: PA.NUS.FCRF | E91: 2019 | F91: 150.03625 | G91: =Table1_1[[#This Row],[Country Name]]&"|"&Table1_1[[#This Row],[Series Name]]&"|"&Table1_1[[#This Row],[Years]] -> Pakistan|Official exchange rate (LCU per US$, period average)|2019
A92: Pakistan | B92: PAK | C92: Official exchange rate (LCU per US$, period average) | D92: PA.NUS.FCRF | E92: 2020 | F92: 161.83848 | G92: =Table1_1[[#This Row],[Country Name]]&"|"&Table1_1[[#This Row],[Series Name]]&"|"&Table1_1[[#This Row],[Years]] -> Pakistan|Official exchange rate (LCU per US$, period average)|2020
A93: Pakistan | B93: PAK | C93: Official exchange rate (LCU per US$, period average) | D93: PA.NUS.FCRF | E93: 2021 | F93: 162.90625 | G93: =Table1_1[[#This Row],[Country Name]]&"|"&Table1_1[[#This Row],[Series Name]]&"|"&Table1_1[[#This Row],[Years]] -> Pakistan|Official exchange rate (LCU per US$, period average)|2021
... A238: India | B238: IND | C238: Lending interest rate (%) | D238: FR.INR.LEND | E238: 2022 | F238: 8.5671429 | G238: =Table1_1[[#This Row],[Country Name]]&"|"&Table1_1[[#This Row],[Series Name]]&"|"&Table1_1[[#This Row],[Years]] -> India|Lending interest rate (%)|2022
A239: India | B239: IND | C239: Lending interest rate (%) | D239: FR.INR.LEND | E239: 2023 | G239: =Table1_1[[#This Row],[Country Name]]&"|"&Table1_1[[#This Row],[Series Name]]&"|"&Table1_1[[#This Row],[Years]] -> India|Lending interest rate (%)|2023
A240: India | B240: IND | C240: Lending interest rate (%) | D240: FR.INR.LEND | E240: 2024 | G240: =Table1_1[[#This Row],[Country Name]]&"|"&Table1_1[[#This Row],[Series Name]]&"|"&Table1_1[[#This Row],[Years]] -> India|Lending interest rate (%)|2024
A241: India | B241: IND | C241: Lending interest rate (%) | D241: FR.INR.LEND | E241: 2025 | G241: =Table1_1[[#This Row],[Country Name]]&"|"&Table1_1[[#This Row],[Series Name]]&"|"&Table1_1[[#This Row],[Years]] -> India|Lending interest rate (%)|2025
A242: India | B242: IND | C242: Official exchange rate (LCU per US$, period average) | D242: PA.NUS.FCRF | E242: 2010 | F242: 45.725812 | G242: =Table1_1[[#This Row],[Country Name]]&"|"&Table1_1[[#This Row],[Series Name]]&"|"&Table1_1[[#This Row],[Years]] -> India|Official exchange rate (LCU per US$, period average)|2010
A243: India | B243: IND | C243: Official exchange rate (LCU per US$, period average) | D243: PA.NUS.FCRF | E243: 2011 | F243: 46.670467 | G243: =Table1_1[[#This Row],[Country Name]]&"|"&Table1_1[[#This Row],[Series Name]]&"|"&Table1_1[[#This Row],[Years]] -> India|Official exchange rate (LCU per US$, period average)|2011
A244: India | B244: IND | C244: Official exchange rate (LCU per US$, period average) | D244: PA.NUS.FCRF | E244: 2012 | F244: 53.437233 | G244: =Table1_1[[#This Row],[Country Name]]&"|"&Table1_1[[#This Row],[Series Name]]&"|"&Table1_1[[#This Row],[Years]] -> India|Official exchange rate (LCU per US$, period average)|2012
A245: India | B245: IND | C245: Official exchange rate (LCU per US$, period average) | D245: PA.NUS.FCRF | E245: 2013 | F245: 58.597845 | G245: =Table1_1[[#This Row],[Country Name]]&"|"&Table1_1[[#This Row],[Series Name]]&"|"&Table1_1[[#This Row],[Years]] -> India|Official exchange rate (LCU per US$, period average)|2013
A246: India | B246: IND | C246: Official exchange rate (LCU per US$, period average) | D246: PA.NUS.FCRF | E246: 2014 | F246: 61.029514 | G246: =Table1_1[[#This Row],[Country Name]]&"|"&Table1_1[[#This Row],[Series Name]]&"|"&Table1_1[[#This Row],[Years]] -> India|Official exchange rate (LCU per US$, period average)|2014
A247: India | B247: IND | C247: Official exchange rate (LCU per US$, period average) | D247: PA.NUS.FCRF | E247: 2015 | F247: 64.151944 | G247: =Table1_1[[#This Row],[Country Name]]&"|"&Table1_1[[#This Row],[Series Name]]&"|"&Table1_1[[#This Row],[Years]] -> India|Official exchange rate (LCU per US$, period average)|2015
A248: India | B248: IND | C248: Official exchange rate (LCU per US$, period average) | D248: PA.NUS.FCRF | E248: 2016 | F248: 67.195313 | G248: =Table1_1[[#This Row],[Country Name]]&"|"&Table1_1[[#This Row],[Series Name]]&"|"&Table1_1[[#This Row],[Years]] -> India|Official exchange rate (LCU per US$, period average)|2016
A249: India | B249: IND | C249: Official exchange rate (LCU per US$, period average) | D249: PA.NUS.FCRF | E249: 2017 | F249: 65.121569 | G249: =Table1_1[[#This Row],[Country Name]]&"|"&Table1_1[[#This Row],[Series Name]]&"|"&Table1_1[[#This Row],[Years]] -> India|Official exchange rate (LCU per US$, period average)|2017
A250: India | B250: IND | C250: Official exchange rate (LCU per US$, period average) | D250: PA.NUS.FCRF | E250: 2018 | F250: 68.389467 | G250: =Table1_1[[#This Row],[Country Name]]&"|"&Table1_1[[#This Row],[Series Name]]&"|"&Table1_1[[#This Row],[Years]] -> India|Official exchange rate (LCU per US$, period average)|2018
A251: India | B251: IND | C251: Official exchange rate (LCU per US$, period average) | D251: PA.NUS.FCRF | E251: 2019 | F251: 70.420341 | G251: =Table1_1[[#This Row],[Country Name]]&"|"&Table1_1[[#This Row],[Series Name]]&"|"&Table1_1[[#This Row],[Years]] -> India|Official exchange rate (LCU per US$, period average)|2019
A252: India | B252: IND | C252: Official exchange rate (LCU per US$, period average) | D252: PA.NUS.FCRF | E252: 2020 | F252: 74.099567 | G252: =Table1_1[[#This Row],[Country Name]]&"|"&Table1_1[[#This Row],[Series Name]]&"|"&Table1_1[[#This Row],[Years]] -> India|Official exchange rate (LCU per US$, period average)|2020
A253: India | B253: IND | C253: Official exchange rate (LCU per US$, period average) | D253: PA.NUS.FCRF | E253: 2021 | F253: 73.918013 | G253: =Table1_1[[#This Row],[Country Name]]&"|"&Table1_1[[#This Row],[Series Name]]&"|"&Table1_1[[#This Row],[Years]] -> India|Official exchange rate (LCU per US$, period average)|2021
... A400: China | B400: CHN | C400: Lending interest rate (%) | D400: FR.INR.LEND | E400: 2024 | F400: 4.35 | G400: =Table1_1[[#This Row],[Country Name]]&"|"&Table1_1[[#This Row],[Series Name]]&"|"&Table1_1[[#This Row],[Years]] -> China|Lending interest rate (%)|2024
A401: China | B401: CHN | C401: Lending interest rate (%) | D401: FR.INR.LEND | E401: 2025 | G401: =Table1_1[[#This Row],[Country Name]]&"|"&Table1_1[[#This Row],[Series Name]]&"|"&Table1_1[[#This Row],[Years]] -> China|Lending interest rate (%)|2025
A402: China | B402: CHN | C402: Official exchange rate (LCU per US$, period average) | D402: PA.NUS.FCRF | E402: 2010 | F402: 6.770269 | G402: =Table1_1[[#This Row],[Country Name]]&"|"&Table1_1[[#This Row],[Series Name]]&"|"&Table1_1[[#This Row],[Years]] -> China|Official exchange rate (LCU per US$, period average)|2010
A403: China | B403: CHN | C403: Official exchange rate (LCU per US$, period average) | D403: PA.NUS.FCRF | E403: 2011 | F403: 6.4614613 | G403: =Table1_1[[#This Row],[Country Name]]&"|"&Table1_1[[#This Row],[Series Name]]&"|"&Table1_1[[#This Row],[Years]] -> China|Official exchange rate (LCU per US$, period average)|2011
A404: China | B404: CHN | C404: Official exchange rate (LCU per US$, period average) | D404: PA.NUS.FCRF | E404: 2012 | F404: 6.3123328 | G404: =Table1_1[[#This Row],[Country Name]]&"|"&Table1_1[[#This Row],[Series Name]]&"|"&Table1_1[[#This Row],[Years]] -> China|Official exchange rate (LCU per US$, period average)|2012
A405: China | B405: CHN | C405: Official exchange rate (LCU per US$, period average) | D405: PA.NUS.FCRF | E405: 2013 | F405: 6.1957583 | G405: =Table1_1[[#This Row],[Country Name]]&"|"&Table1_1[[#This Row],[Series Name]]&"|"&Table1_1[[#This Row],[Years]] -> China|Official exchange rate (LCU per US$, period average)|2013
A406: China | B406: CHN | C406: Official exchange rate (LCU per US$, period average) | D406: PA.NUS.FCRF | E406: 2014 | F406: 6.1434341 | G406: =Table1_1[[#This Row],[Country Name]]&"|"&Table1_1[[#This Row],[Series Name]]&"|"&Table1_1[[#This Row],[Years]] -> China|Official exchange rate (LCU per US$, period average)|2014
A407: China | B407: CHN | C407: Official exchange rate (LCU per US$, period average) | D407: PA.NUS.FCRF | E407: 2015 | F407: 6.2274887 | G407: =Table1_1[[#This Row],[Country Name]]&"|"&Table1_1[[#This Row],[Series Name]]&"|"&Table1_1[[#This Row],[Years]] -> China|Official exchange rate (LCU per US$, period average)|2015
A408: China | B408: CHN | C408: Official exchange rate (LCU per US$, period average) | D408: PA.NUS.FCRF | E408: 2016 | F408: 6.6444778 | G408: =Table1_1[[#This Row],[Country Name]]&"|"&Table1_1[[#This Row],[Series Name]]&"|"&Table1_1[[#This Row],[Years]] -> China|Official exchange rate (LCU per US$, period average)|2016
A409: China | B409: CHN | C409: Official exchange rate (LCU per US$, period average) | D409: PA.NUS.FCRF | E409: 2017 | F409: 6.7587551 | G409: =Table1_1[[#This Row],[Country Name]]&"|"&Table1_1[[#This Row],[Series Name]]&"|"&Table1_1[[#This Row],[Years]] -> China|Official exchange rate (LCU per US$, period average)|2017
A410: China | B410: CHN | C410: Official exchange rate (LCU per US$, period average) | D410: PA.NUS.FCRF | E410: 2018 | F410: 6.6159572 | G410: =Table1_1[[#This Row],[Country Name]]&"|"&Table1_1[[#This Row],[Series Name]]&"|"&Table1_1[[#This Row],[Years]] -> China|Official exchange rate (LCU per US$, period average)|2018
A411: China | B411: CHN | C411: Official exchange rate (LCU per US$, period average) | D411: PA.NUS.FCRF | E411: 2019 | F411: 6.908385 | G411: =Table1_1[[#This Row],[Country Name]]&"|"&Table1_1[[#This Row],[Series Name]]&"|"&Table1_1[[#This Row],[Years]] -> China|Official exchange rate (LCU per US$, period average)|2019
A412: China | B412: CHN | C412: Official exchange rate (LCU per US$, period average) | D412: PA.NUS.FCRF | E412: 2020 | F412: 6.9007673 | G412: =Table1_1[[#This Row],[Country Name]]&"|"&Table1_1[[#This Row],[Series Name]]&"|"&Table1_1[[#This Row],[Years]] -> China|Official exchange rate (LCU per US$, period average)|2020
A413: China | B413: CHN | C413: Official exchange rate (LCU per US$, period average) | D413: PA.NUS.FCRF | E413: 2021 | F413: 6.4489752 | G413: =Table1_1[[#This Row],[Country Name]]&"|"&Table1_1[[#This Row],[Series Name]]&"|"&Table1_1[[#This Row],[Years]] -> China|Official exchange rate (LCU per US$, period average)|2021
... A553: Japan | B553: JPN | C553: Lending interest rate (%) | D553: FR.INR.LEND | E553: 2017 | F553: 0.994 | G553: =Table1_1[[#This Row],[Country Name]]&"|"&Table1_1[[#This Row],[Series Name]]&"|"&Table1_1[[#This Row],[Years]] -> Japan|Lending interest rate (%)|2017
A554: Japan | B554: JPN | C554: Lending interest rate (%) | D554: FR.INR.LEND | E554: 2018 | G554: =Table1_1[[#This Row],[Country Name]]&"|"&Table1_1[[#This Row],[Series Name]]&"|"&Table1_1[[#This Row],[Years]] -> Japan|Lending interest rate (%)|2018
A555: Japan | B555: JPN | C555: Lending interest rate (%) | D555: FR.INR.LEND | E555: 2019 | G555: =Table1_1[[#This Row],[Country Name]]&"|"&Table1_1[[#This Row],[Series Name]]&"|"&Table1_1[[#This Row],[Years]] -> Japan|Lending interest rate (%)|2019
A556: Japan | B556: JPN | C556: Lending interest rate (%) | D556: FR.INR.LEND | E556: 2020 | G556: =Table1_1[[#This Row],[Country Name]]&"|"&Table1_1[[#This Row],[Series Name]]&"|"&Table1_1[[#This Row],[Years]] -> Japan|Lending interest rate (%)|2020
A557: Japan | B557: JPN | C557: Lending interest rate (%) | D557: FR.INR.LEND | E557: 2021 | G557: =Table1_1[[#This Row],[Country Name]]&"|"&Table1_1[[#This Row],[Series Name]]&"|"&Table1_1[[#This Row],[Years]] -> Japan|Lending interest rate (%)|2021
A558: Japan | B558: JPN | C558: Lending interest rate (%) | D558: FR.INR.LEND | E558: 2022 | G558: =Table1_1[[#This Row],[Country Name]]&"|"&Table1_1[[#This Row],[Series Name]]&"|"&Table1_1[[#This Row],[Years]] -> Japan|Lending interest rate (%)|2022
A559: Japan | B559: JPN | C559: Lending interest rate (%) | D559: FR.INR.LEND | E559: 2023 | G559: =Table1_1[[#This Row],[Country Name]]&"|"&Table1_1[[#This Row],[Series Name]]&"|"&Table1_1[[#This Row],[Years]] -> Japan|Lending interest rate (%)|2023
A560: Japan | B560: JPN | C560: Lending interest rate (%) | D560: FR.INR.LEND | E560: 2024 | G560: =Table1_1[[#This Row],[Country Name]]&"|"&Table1_1[[#This Row],[Series Name]]&"|"&Table1_1[[#This Row],[Years]] -> Japan|Lending interest rate (%)|2024
A561: Japan | B561: JPN | C561: Lending interest rate (%) | D561: FR.INR.LEND | E561: 2025 | G561: =Table1_1[[#This Row],[Country Name]]&"|"&Table1_1[[#This Row],[Series Name]]&"|"&Table1_1[[#This Row],[Years]] -> Japan|Lending interest rate (%)|2025
A562: Japan | B562: JPN | C562: Official exchange rate (LCU per US$, period average) | D562: PA.NUS.FCRF | E562: 2010 | F562: 87.779875 | G562: =Table1_1[[#This Row],[Country Name]]&"|"&Table1_1[[#This Row],[Series Name]]&"|"&Table1_1[[#This Row],[Years]] -> Japan|Official exchange rate (LCU per US$, period average)|2010
A563: Japan | B563: JPN | C563: Official exchange rate (LCU per US$, period average) | D563: PA.NUS.FCRF | E563: 2011 | F563: 79.80702 | G563: =Table1_1[[#This Row],[Country Name]]&"|"&Table1_1[[#This Row],[Series Name]]&"|"&Table1_1[[#This Row],[Years]] -> Japan|Official exchange rate (LCU per US$, period average)|2011
A564: Japan | B564: JPN | C564: Official exchange rate (LCU per US$, period average) | D564: PA.NUS.FCRF | E564: 2012 | F564: 79.790455 | G564: =Table1_1[[#This Row],[Country Name]]&"|"&Table1_1[[#This Row],[Series Name]]&"|"&Table1_1[[#This Row],[Years]] -> Japan|Official exchange rate (LCU per US$, period average)|2012
A565: Japan | B565: JPN | C565: Official exchange rate (LCU per US$, period average) | D565: PA.NUS.FCRF | E565: 2013 | F565: 97.595658 | G565: =Table1_1[[#This Row],[Country Name]]&"|"&Table1_1[[#This Row],[Series Name]]&"|"&Table1_1[[#This Row],[Years]] -> Japan|Official exchange rate (LCU per US$, period average)|2013
A566: Japan | B566: JPN | C566: Official exchange rate (LCU per US$, period average) | D566: PA.NUS.FCRF | E566: 2014 | F566: 105.94478 | G566: =Table1_1[[#This Row],[Country Name]]&"|"&Table1_1[[#This Row],[Series Name]]&"|"&Table1_1[[#This Row],[Years]] -> Japan|Official exchange rate (LCU per US$, period average)|2014
A567: Japan | B567: JPN | C567: Official exchange rate (LCU per US$, period average) | D567: PA.NUS.FCRF | E567: 2015 | F567: 121.04403 | G567: =Table1_1[[#This Row],[Country Name]]&"|"&Table1_1[[#This Row],[Series Name]]&"|"&Table1_1[[#This Row],[Years]] -> Japan|Official exchange rate (LCU per US$, period average)|2015
A568: Japan | B568: JPN | C568: Official exchange rate (LCU per US$, period average) | D568: PA.NUS.FCRF | E568: 2016 | F568: 108.7929 | G568: =Table1_1[[#This Row],[Country Name]]&"|"&Table1_1[[#This Row],[Series Name]]&"|"&Table1_1[[#This Row],[Years]] -> Japan|Official exchange rate (LCU per US$, period average)|2016
A569: Japan | B569: JPN | C569: Official exchange rate (LCU per US$, period average) | D569: PA.NUS.FCRF | E569: 2017 | F569: 112.16614 | G569: =Table1_1[[#This Row],[Country Name]]&"|"&Table1_1[[#This Row],[Series Name]]&"|"&Table1_1[[#This Row],[Years]] -> Japan|Official exchange rate (LCU per US$, period average)|2017
A570: Japan | B570: JPN | C570: Official exchange rate (LCU per US$, period average) | D570: PA.NUS.FCRF | E570: 2018 | F570: 110.42318 | G570: =Table1_1[[#This Row],[Country Name]]&"|"&Table1_1[[#This Row],[Series Name]]&"|"&Table1_1[[#This Row],[Years]] -> Japan|Official exchange rate (LCU per US$, period average)|2018
A571: Japan | B571: JPN | C571: Official exchange rate (LCU per US$, period average) | D571: PA.NUS.FCRF | E571: 2019 | F571: 109.00967 | G571: =Table1_1[[#This Row],[Country Name]]&"|"&Table1_1[[#This Row],[Series Name]]&"|"&Table1_1[[#This Row],[Years]] -> Japan|Official exchange rate (LCU per US$, period average)|2019
A572: Japan | B572: JPN | C572: Official exchange rate (LCU per US$, period average) | D572: PA.NUS.FCRF | E572: 2020 | F572: 106.77458 | G572: =Table1_1[[#This Row],[Country Name]]&"|"&Table1_1[[#This Row],[Series Name]]&"|"&Table1_1[[#This Row],[Years]] -> Japan|Official exchange rate (LCU per US$, period average)|2020
A573: Japan | B573: JPN | C573: Official exchange rate (LCU per US$, period average) | D573: PA.NUS.FCRF | E573: 2021 | F573: 109.75432 | G573: =Table1_1[[#This Row],[Country Name]]&"|"&Table1_1[[#This Row],[Series Name]]&"|"&Table1_1[[#This Row],[Years]] -> Japan|Official exchange rate (LCU per US$, period average)|2021
... A592: Japan | B592: JPN | C592: Exports of goods and services (% of GDP) | D592: NE.EXP.GNFS.ZS | E592: 2024 | F592: 21.979909 | G592: =Table1_1[[#This Row],[Country Name]]&"|"&Table1_1[[#This Row],[Series Name]]&"|"&Table1_1[[#This Row],[Years]] -> Japan|Exports of goods and services (% of GDP)|2024
A593: Japan | B593: JPN | C593: Exports of goods and services (% of GDP) | D593: NE.EXP.GNFS.ZS | E593: 2025 | G593: =Table1_1[[#This Row],[Country Name]]&"|"&Table1_1[[#This Row],[Series Name]]&"|"&Table1_1[[#This Row],[Years]] -> Japan|Exports of goods and services (% of GDP)|2025
A594: Japan | B594: JPN | C594: Imports of goods and services (% of GDP) | D594: NE.IMP.GNFS.ZS | E594: 2010 | F594: 13.457277 | G594: =Table1_1[[#This Row],[Country Name]]&"|"&Table1_1[[#This Row],[Series Name]]&"|"&Table1_1[[#This Row],[Years]] -> Japan|Imports of goods and services (% of GDP)|2010
A595: Japan | B595: JPN | C595: Imports of goods and services (% of GDP) | D595: NE.IMP.GNFS.ZS | E595: 2011 | F595: 15.306859 | G595: =Table1_1[[#This Row],[Country Name]]&"|"&Table1_1[[#This Row],[Series Name]]&"|"&Table1_1[[#This Row],[Years]] -> Japan|Imports of goods and services (% of GDP)|2011
A596: Japan | B596: JPN | C596: Imports of goods and services (% of GDP) | D596: NE.IMP.GNFS.ZS | E596: 2012 | F596: 15.900384 | G596: =Table1_1[[#This Row],[Country Name]]&"|"&Table1_1[[#This Row],[Series Name]]&"|"&Table1_1[[#This Row],[Years]] -> Japan|Imports of goods and services (% of GDP)|2012
A597: Japan | B597: JPN | C597: Imports of goods and services (% of GDP) | D597: NE.IMP.GNFS.ZS | E597: 2013 | F597: 17.98766 | G597: =Table1_1[[#This Row],[Country Name]]&"|"&Table1_1[[#This Row],[Series Name]]&"|"&Table1_1[[#This Row],[Years]] -> Japan|Imports of goods and services (% of GDP)|2013
A598: Japan | B598: JPN | C598: Imports of goods and services (% of GDP) | D598: NE.IMP.GNFS.ZS | E598: 2014 | F598: 19.656462 | G598: =Table1_1[[#This Row],[Country Name]]&"|"&Table1_1[[#This Row],[Series Name]]&"|"&Table1_1[[#This Row],[Years]] -> Japan|Imports of goods and services (% of GDP)|2014
A599: Japan | B599: JPN | C599: Imports of goods and services (% of GDP) | D599: NE.IMP.GNFS.ZS | E599: 2015 | F599: 17.635521 | G599: =Table1_1[[#This Row],[Country Name]]&"|"&Table1_1[[#This Row],[Series Name]]&"|"&Table1_1[[#This Row],[Years]] -> Japan|Imports of goods and services (% of GDP)|2015
A600: Japan | B600: JPN | C600: Imports of goods and services (% of GDP) | D600: NE.IMP.GNFS.ZS | E600: 2016 | F600: 14.933883 | G600: =Table1_1[[#This Row],[Country Name]]&"|"&Table1_1[[#This Row],[Series Name]]&"|"&Table1_1[[#This Row],[Years]] -> Japan|Imports of goods and services (% of GDP)|2016
A601: Japan | B601: JPN | C601: Imports of goods and services (% of GDP) | D601: NE.IMP.GNFS.ZS | E601: 2017 | F601: 16.473008 | G601: =Table1_1[[#This Row],[Country Name]]&"|"&Table1_1[[#This Row],[Series Name]]&"|"&Table1_1[[#This Row],[Years]] -> Japan|Imports of goods and services (% of GDP)|2017
A602: Japan | B602: JPN | C602: Imports of goods and services (% of GDP) | D602: NE.IMP.GNFS.ZS | E602: 2018 | F602: 17.892431 | G602: =Table1_1[[#This Row],[Country Name]]&"|"&Table1_1[[#This Row],[Series Name]]&"|"&Table1_1[[#This Row],[Years]] -> Japan|Imports of goods and services (% of GDP)|2018
A603: Japan | B603: JPN | C603: Imports of goods and services (% of GDP) | D603: NE.IMP.GNFS.ZS | E603: 2019 | F603: 17.3205 | G603: =Table1_1[[#This Row],[Country Name]]&"|"&Table1_1[[#This Row],[Series Name]]&"|"&Table1_1[[#This Row],[Years]] -> Japan|Imports of goods and services (% of GDP)|2019
A604: Japan | B604: JPN | C604: Imports of goods and services (% of GDP) | D604: NE.IMP.GNFS.ZS | E604: 2020 | F604: 15.390532 | G604: =Table1_1[[#This Row],[Country Name]]&"|"&Table1_1[[#This Row],[Series Name]]&"|"&Table1_1[[#This Row],[Years]] -> Japan|Imports of goods and services (% of GDP)|2020
A605: Japan | B605: JPN | C605: Imports of goods and services (% of GDP) | D605: NE.IMP.GNFS.ZS | E605: 2021 | F605: 17.963407 | G605: =Table1_1[[#This Row],[Country Name]]&"|"&Table1_1[[#This Row],[Series Name]]&"|"&Table1_1[[#This Row],[Years]] -> Japan|Imports of goods and services (% of GDP)|2021
... A608: Japan | B608: JPN | C608: Imports of goods and services (% of GDP) | D608: NE.IMP.GNFS.ZS | E608: 2024 | F608: 22.873029 | G608: =Table1_1[[#This Row],[Country Name]]&"|"&Table1_1[[#This Row],[Series Name]]&"|"&Table1_1[[#This Row],[Years]] -> Japan|Imports of goods and services (% of GDP)|2024
A609: Japan | B609: JPN | C609: Imports of goods and services (% of GDP) | D609: NE.IMP.GNFS.ZS | E609: 2025 | G609: =Table1_1[[#This Row],[Country Name]]&"|"&Table1_1[[#This Row],[Series Name]]&"|"&Table1_1[[#This Row],[Years]] -> Japan|Imports of goods and services (% of GDP)|2025
A610: Japan | B610: JPN | C610: Foreign direct investment, net inflows (BoP, current US$) | D610: BX.KLT.DINV.CD.WD | E610: 2010 | F610: 7.4409793e+09 | G610: =Table1_1[[#This Row],[Country Name]]&"|"&Table1_1[[#This Row],[Series Name]]&"|"&Table1_1[[#This Row],[Years]] -> Japan|Foreign direct investment, net inflows (BoP, current US$)|2010
A611: Japan | B611: JPN | C611: Foreign direct investment, net inflows (BoP, current US$) | D611: BX.KLT.DINV.CD.WD | E611: 2011 | F611: -8.5071704e+08 | G611: =Table1_1[[#This Row],[Country Name]]&"|"&Table1_1[[#This Row],[Series Name]]&"|"&Table1_1[[#This Row],[Years]] -> Japan|Foreign direct investment, net inflows (BoP, current US$)|2011
A612: Japan | B612: JPN | C612: Foreign direct investment, net inflows (BoP, current US$) | D612: BX.KLT.DINV.CD.WD | E612: 2012 | F612: 5.4696269e+08 | G612: =Table1_1[[#This Row],[Country Name]]&"|"&Table1_1[[#This Row],[Series Name]]&"|"&Table1_1[[#This Row],[Years]] -> Japan|Foreign direct investment, net inflows (BoP, current US$)|2012
...

Sheet PIVOTS
A1: Average GDP Growth by Country → comparison | E1: Series Name | F1: GDP growth (annual %) | I1: Country × Indicator → overall economic summary | L1: Series Name | M1: GDP (current US$) | O1: GDP by Country & Year → GDP comparison
D2: GDP Growth by Year
A3: Row Labels | B3: Average of Average GDP Growth (2010–2025) | E3: Row Labels | F3: Sum of Value | I3: Row Labels | J3: Average of Value | L3: Sum of Value | M3: Column Labels
A4: Australia | B4: 2.4080295 | E4: 2010 | F4: 49.676573 | I4: Australia | J4: 1.5931801e+11 | L4: Row Labels | M4: 2025 | N4: Grand Total
A5: China | B5: 6.6250458 | E5: 2011 | F5: 37.215373 | I5: Exports of goods and services (% of GDP) | J5: 22.226044 | L5: Australia | M5: 1.7985189e+12 | N5: 1.7985189e+12
A6: Germany | B6: 1.2619555 | E6: 2012 | F6: 37.727588 | I6: Foreign direct investment, net inflows (BoP, current US$) | J6: 4.734845e+10 | L6: China | M6: 1.9498039e+13 | N6: 1.9498039e+13
A7: India | B7: 6.2351407 | E7: 2013 | F7: 37.667412 | I7: GDP (current US$) | J7: 1.4860627e+12 | L7: Germany | M7: 5.0509229e+12 | N7: 5.0509229e+12
A8: Indonesia | B8: 4.7684027 | E8: 2014 | F8: 41.372338 | I8: GDP growth (annual %) | J8: 2.4080295 | L8: India | M8: 3.9560671e+12 | N8: 3.9560671e+12
A9: Japan | B9: 0.96429146 | E9: 2015 | F9: 39.87696 | I9: Imports of goods and services (% of GDP) | J9: 21.207596 | L9: Indonesia | M9: 1.4456426e+12 | N9: 1.4456426e+12
A10: Malaysia | B10: 4.6379377 | E10: 2016 | F10: 40.795504 | I10: Inflation, consumer prices (annual %) | J10: 2.695093 | L10: Japan | M10: 4.435163e+12 | N10: 4.435163e+12
A11: Pakistan | B11: 3.496851 | E11: 2017 | F11: 41.197269 | I11: Lending interest rate (%) | J11: 6.0724 | L11: Malaysia | M11: 4.7219313e+11 | N11: 4.7219313e+11
A12: United Kingdom | B12: 1.630122 | E12: 2018 | F12: 38.742585 | I12: Official exchange rate (LCU per US$, period average) | J12: 1.2954457 | L12: Pakistan | M12: 4.0730721e+11 | N12: 4.0730721e+11
A13: United States | B13: 2.4029444 | E13: 2019 | F13: 28.572306 | I13: Population, total | J13: 24714289 | L13: United Kingdom | M13: 4.0025875e+12 | N13: 4.0025875e+12
A14: Grand Total | B14: 3.4430721 | E14: 2020 | F14: -32.912665 | I14: Unemployment, total (% of total labor force) (modeled ILO estimate) | J14: 5.1220625 | L14: United States | M14: 30769700000000 | N14: 30769700000000
E15: 2021 | F15: 55.968376 | I15: China | J15: 1.3727317e+12 | L15: Grand Total | M15: 7.1836142e+13 | N15: 7.1836142e+13
E16: 2022 | F16: 44.92813 | I16: Exports of goods and services (% of GDP) | J16: 21.276506
E17: 2023 | F17: 27.438159 | I17: Foreign direct investment, net inflows (BoP, current US$) | J17: 2.0570072e+11
E18: 2024 | F18: 29.788316 | I18: GDP (current US$) | J18: 1.3434432e+13
E19: 2025 | F19: 32.83731 | I19: GDP growth (annual %) | J19: 6.6250458
A20: Average Inflation by Country → inflation comparison | E20: Grand Total | F20: 550.89153 | I20: Imports of goods and services (% of GDP) | J20: 18.88496 | L20: GDP Growth vs Inflation | Q20: Country Name | R20: (All)
A21: Series Name | B21: (All) | I21: Inflation, consumer prices (annual %) | J21: 1.9863856 | L21: Average of Value | M21: Column Labels
I22: Lending interest rate (%) | J22: 4.898 | L22: Row Labels | M22: GDP growth (annual %) | N22: Inflation, consumer prices (annual %) | O22: Grand Total | Q22: Average of Value | R22: Column Labels
A23: Row Labels | B23: Average of Value | I23: Official exchange rate (LCU per US$, period average) | J23: 6.6622848 | L23: Australia | M23: 2.4080295 | N23: 2.695093 | O23: 2.5515613 | Q23: Row Labels | R23: GDP (current US$) | S23: GDP growth (annual %) | T23: Inflation, consumer prices (annual %) | U23: Grand Total
A24: Australia | B24: 1.5931801e+11 | I24: Population, total | J24: 1.3880191e+09 | L24: China | M24: 6.6250458 | N24: 1.9863856 | O24: 4.3057157 | Q24: 2010 | R24: 3.7051952e+12 | S24: 4.9676573 | T24: 4.2287246 | U24: 1.2350651e+12
A25: China | B25: 1.3727317e+12 | I25: Unemployment, total (% of total labor force) (modeled ILO estimate) | J25: 4.6153125 | L25: Germany | M25: 1.2619555 | N25: 2.109458 | O25: 1.6857067 | Q25: 2011 | R25: 4.0697577e+12 | S25: 3.7215373 | T25: 4.7031823 | U25: 1.3565859e+12
A26: Germany | B26: 4.557613e+11 | I26: Germany | J26: 4.557613e+11 | L26: India | M26: 6.2351407 | N26: 6.2106448 | O26: 6.2228928 | Q26: 2012 | R26: 4.2440424e+12 | S26: 3.7727588 | T26: 3.6093738 | U26: 1.4146808e+12
A27: India | B27: 2.7240327e+11 | I27: Exports of goods and services (% of GDP) | J27: 41.91023 | L27: Indonesia | M27: 4.7684027 | N27: 3.9348413 | O27: 4.351622 | Q27: 2013 | R27: 4.3434953e+12 | S27: 3.7667412 | T27: 3.6894735 | U27: 1.4478318e+12
A28: Indonesia | B28: 1.0905274e+11 | I28: Foreign direct investment, net inflows (BoP, current US$) | J28: 8.9393738e+10 | L28: Japan | M28: 0.96429146 | N28: 1.0048842 | O28: 0.98458784 | Q28: 2014 | R28: 4.5332742e+12 | S28: 4.1372338 | T28: 3.4541895 | U28: 1.5110914e+12
A29: Japan | B29: 5.4692897e+11 | I29: GDP (current US$) | J29: 4.0123756e+12 | L29: Malaysia | M29: 4.6379377 | N29: 1.9839581 | O29: 3.3109479 | Q29: 2015 | R29: 4.5403519e+12 | S29: 3.987696 | T29: 2.0645584 | U29: 1.5134506e+12
A30: Malaysia | B30: 3.6215205e+10 | I30: GDP growth (annual %) | J30: 1.2619555 | L30: Pakistan | M30: 3.496851 | N30: 10.094461 | O30: 6.7956558 | Q30: 2016 | R30: 4.6668038e+12 | S30: 4.0795504 | T30: 2.0241191 | U30: 1.5556013e+12
A31: Pakistan | B31: 3.2120907e+10 | I31: Imports of goods and services (% of GDP) | J31: 36.633836 | L31: United Kingdom | M31: 1.630122 | N31: 2.8755293 | O31: 2.2528257 | Q31: 2017 | R31: 4.9308661e+12 | S31: 4.1197269 | T31: 2.5316886 | U31: 1.643622e+12
A32: United Kingdom | B32: 3.3082084e+11 | I32: Inflation, consumer prices (annual %) | J32: 2.109458 | L32: United States | M32: 2.4029444 | N32: 2.5812332 | O32: 2.4892132 | Q32: 2018 | R32: 5.28043e+12 | S32: 3.8742585 | T32: 2.4542817 | U32: 1.7601433e+12
A33: United States | B33: 2.2525926e+12 | I33: Lending interest rate (%) | L33: Grand Total | M33: 3.4430721 | N33: 3.5537269 | O33: 3.498226 | Q33: 2019 | R33: 5.4220652e+12 | S33: 2.8572306 | T33: 2.7975768 | U33: 1.8073551e+12
A34: Grand Total | B34: 5.5508895e+11 | I34: Official exchange rate (LCU per US$, period average) | J34: 0.84943931 | Q34: 2020 | R34: 5.3931418e+12 | S34: -3.2912665 | T34: 2.2753962 | U34: 1.7977139e+12
I35: Population, total | J35: 82289172 | Q35: 2021 | R35: 6.1339787e+12 | S35: 5.5968376 | T35: 3.2559476 | U35: 2.0446596e+12
I36: Unemployment, total (% of total labor force) (modeled ILO estimate) | J36: 4.2821875 | Q36: 2022 | R36: 6.3249009e+12 | S36: 4.492813 | T36: 6.8023855 | U36: 2.1083003e+12
I37: India | J37: 2.7240327e+11 | Q37: 2023 | R37: 6.5792892e+12 | S37: 2.7438159 | T37: 6.8532254 | U37: 2.1930964e+12
I38: Exports of goods and services (% of GDP) | J38: 21.689595 | Q38: 2024 | R38: 6.8306934e+12 | S38: 2.9788316 | T38: 3.6202009 | U38: 2.2768978e+12
I39: Foreign direct investment, net inflows (BoP, current US$) | J39: 3.9071021e+10 | Q39: 2025 | R39: 7.1836142e+12 | S39: 3.283731 | T39: 2.3777038 | U39: 2.4771083e+12
I40: GDP (current US$) | J40: 2.6325247e+12 | Q40: Grand Total | R40: 5.2613687e+12 | S40: 3.4430721 | T40: 3.5537269 | U40: 1.7574509e+12
I41: GDP growth (annual %) | J41: 6.2351407
I42: Imports of goods and services (% of GDP) | J42: 24.691429
I43: Inflation, consumer prices (annual %) | J43: 6.2106448
I44: Lending interest rate (%) | J44: 9.5516084
I45: Official exchange rate (LCU per US$, period average) | J45: 67.549286
I46: Population, total | J46: 1.3613699e+09
I47: Unemployment, total (% of total labor force) (modeled ILO estimate) | J47: 6.6795
I48: Indonesia | J48: 1.0905274e+11
I49: Exports of goods and services (% of GDP) | J49: 22.065404
I50: Foreign direct investment, net inflows (BoP, current US$) | J50: 2.0461685e+10
I51: GDP (current US$) | J51: 1.0697982e+12
I52: GDP growth (annual %) | J52: 4.7684027
... I114: Grand Total | J114: 5.5508895e+11

Sheet Analysis
A1: Column1 | B1: Column2 | C1: Column3
A2: Country & Year Lookup
A3: country | B3: year | C3: indicator | D3: value | E3: Lookuup
A4: Pakistan | B4: 2025 | C4: GDP growth (annual %) | D4: =SUMIFS(Table1!F:F,Table1!A:A,Analysis!A4,Table1!E:E,Analysis!B4,Table1!C:C,Analysis!C4) -> 3.6984267 | E4: =A4&"|"&C4&"|"&B4 -> Pakistan|GDP growth (annual %)|2025
A6: Country Comparision | B6: Column1 | C6: Column2
A7: Country | B7: Average GDP Growth (2010–2025) | C7: Years GDP Growth > 5%
A8: Pakistan | B8: =IFERROR(AVERAGEIFS(Table1!F:F,Table1!A:A,Analysis!A8,Table1!C:C,"GDP growth (annual %)"),"N/A") -> 3.496851 | C8: =COUNTIFS(Table1!A:A,Analysis!A8,Table1!C:C,"GDP growth (annual %)",Table1!F:F,">5") -> 3
A9: India | B9: =IFERROR(AVERAGEIFS(Table1!F:F,Table1!A:A,Analysis!A9,Table1!C:C,"GDP growth (annual %)"),"N/A") -> 6.2351407 | C9: =COUNTIFS(Table1!A:A,Analysis!A9,Table1!C:C,"GDP growth (annual %)",Table1!F:F,">5") -> 14
A10: China | B10: =IFERROR(AVERAGEIFS(Table1!F:F,Table1!A:A,Analysis!A10,Table1!C:C,"GDP growth (annual %)"),"N/A") -> 6.6250458 | C10: =COUNTIFS(Table1!A:A,Analysis!A10,Table1!C:C,"GDP growth (annual %)",Table1!F:F,">5") -> 12
A11: Japan | B11: =IFERROR(AVERAGEIFS(Table1!F:F,Table1!A:A,Analysis!A11,Table1!C:C,"GDP growth (annual %)"),"N/A") -> 0.96429146 | C11: =COUNTIFS(Table1!A:A,Analysis!A11,Table1!C:C,"GDP growth (annual %)",Table1!F:F,">5") -> 0
A12: Indonesia | B12: =IFERROR(AVERAGEIFS(Table1!F:F,Table1!A:A,Analysis!A12,Table1!C:C,"GDP growth (annual %)"),"N/A") -> 4.7684027 | C12: =COUNTIFS(Table1!A:A,Analysis!A12,Table1!C:C,"GDP growth (annual %)",Table1!F:F,">5") -> 13
A13: Malaysia | B13: =IFERROR(AVERAGEIFS(Table1!F:F,Table1!A:A,Analysis!A13,Table1!C:C,"GDP growth (annual %)"),"N/A") -> 4.6379377 | C13: =COUNTIFS(Table1!A:A,Analysis!A13,Table1!C:C,"GDP growth (annual %)",Table1!F:F,">5") -> 9
A14: Germany | B14: =IFERROR(AVERAGEIFS(Table1!F:F,Table1!A:A,Analysis!A14,Table1!C:C,"GDP growth (annual %)"),"N/A") -> 1.2619555 | C14: =COUNTIFS(Table1!A:A,Analysis!A14,Table1!C:C,"GDP growth (annual %)",Table1!F:F,">5") -> 0
A15: United Kingdom | B15: =IFERROR(AVERAGEIFS(Table1!F:F,Table1!A:A,Analysis!A15,Table1!C:C,"GDP growth (annual %)"),"N/A") -> 1.630122 | C15: =COUNTIFS(Table1!A:A,Analysis!A15,Table1!C:C,"GDP growth (annual %)",Table1!F:F,">5") -> 2
A16: United States | B16: =IFERROR(AVERAGEIFS(Table1!F:F,Table1!A:A,Analysis!A16,Table1!C:C,"GDP growth (annual %)"),"N/A") -> 2.4029444 | C16: =COUNTIFS(Table1!A:A,Analysis!A16,Table1!C:C,"GDP growth (annual %)",Table1!F:F,">5") -> 1
A17: Australia | B17: =IFERROR(AVERAGEIFS(Table1!F:F,Table1!A:A,Analysis!A17,Table1!C:C,"GDP growth (annual %)"),"N/A") -> 2.4080295 | C17: =COUNTIFS(Table1!A:A,Analysis!A17,Table1!C:C,"GDP growth (annual %)",Table1!F:F,">5") -> 0

Sheet Dashboard
A1: GLOBAL ECONOMIC ANALYSIS DASHBOARD
B2: World Bank Data | 2010–2025
U3: Countries Analyzed | V3: 10
U4: Years Covered | V4: 2010–2025
U5: Indicator | V5: 10
U8: FILTER BY COUNTRY
